[
  {
    "id": "Z147955",
    "nom": "REBBANI",
    "prenom": "AHMED",
    "numero_examen": 1042,
    "salle_examen": "Amphitheatre",
    "epreuve": "MI"
  },
  {
    "id": "E146059194",
    "nom": "Aadioui",
    "prenom": "Soufiane",
    "numero_examen": 1001,
    "salle_examen": "Amphitheatre",
    "epreuve": "MI"
  },
  {
    "id": "D136881360",
    "nom": "Aandadi",
    "prenom": "Asmaa",
    "numero_examen": 1002,
    "salle_examen": "Amphitheatre",
    "epreuve": "MI"
  },
  {
    "id": "D136623923",
    "nom": "Abayda",
    "prenom": "Youssef",
    "numero_examen": 1003,
    "salle_examen": "Amphitheatre",
    "epreuve": "MI"
  },
  {
    "id": "F133178284",
    "nom": "Abba",
    "prenom": "Salma",
    "numero_examen": 1004,
    "salle_examen": "Amphitheatre",
    "epreuve": "MI"
  },
  {
    "id": "L148062724",
    "nom": "Abbadi",
    "prenom": "Meryam",
    "numero_examen": 1005,
    "salle_examen": "Amphitheatre",
    "epreuve": "MI"
  },
  {
    "id": "G130357014",
    "nom": "Abbahoum",
    "prenom": "Meriem",
    "numero_examen": 1006,
    "salle_examen": "Amphitheatre",
    "epreuve": "MI"
  },
  {
    "id": "F100067326",
    "nom": "Abdalli",
    "prenom": "Fatima",
    "numero_examen": 1007,
    "salle_examen": "Amphitheatre",
    "epreuve": "MI"
  },
  {
    "id": "F132197503",
    "nom": "Abdaoui",
    "prenom": "Abdessamad",
    "numero_examen": 1008,
    "salle_examen": "Amphitheatre",
    "epreuve": "MI"
  },
  {
    "id": "F120003011",
    "nom": "Abdelkhalek",
    "prenom": "Mohammed",
    "numero_examen": 1009,
    "salle_examen": "Amphitheatre",
    "epreuve": "MI"
  },
  {
    "id": "D130618913",
    "nom": "Abdelouahd",
    "prenom": "Youssef",
    "numero_examen": 1010,
    "salle_examen": "Amphitheatre",
    "epreuve": "MI"
  },
  {
    "id": "L145062680",
    "nom": "Abi Dahou",
    "prenom": "Aya",
    "numero_examen": 1011,
    "salle_examen": "Amphitheatre",
    "epreuve": "MI"
  },
  {
    "id": "D130439657",
    "nom": "Abib",
    "prenom": "Abdelwahab",
    "numero_examen": 1012,
    "salle_examen": "Amphitheatre",
    "epreuve": "MI"
  },
  {
    "id": "J130040565",
    "nom": "Abou Eljihad",
    "prenom": "Youssef",
    "numero_examen": 1013,
    "salle_examen": "Amphitheatre",
    "epreuve": "MI"
  },
  {
    "id": "L139311029",
    "nom": "Aboufaris",
    "prenom": "Wassima",
    "numero_examen": 1014,
    "salle_examen": "Amphitheatre",
    "epreuve": "MI"
  },
  {
    "id": "E137171721",
    "nom": "Aboulhoda",
    "prenom": "Saad",
    "numero_examen": 1015,
    "salle_examen": "Amphitheatre",
    "epreuve": "MI"
  },
  {
    "id": "J110073405",
    "nom": "Aboumlik",
    "prenom": "Hamza",
    "numero_examen": 1016,
    "salle_examen": "Amphitheatre",
    "epreuve": "MI"
  },
  {
    "id": "R143109942",
    "nom": "Aboussaad",
    "prenom": "Rokaya",
    "numero_examen": 1017,
    "salle_examen": "Amphitheatre",
    "epreuve": "MI"
  },
  {
    "id": "D131623008",
    "nom": "Aboussabre",
    "prenom": "Oumaima",
    "numero_examen": 1018,
    "salle_examen": "Amphitheatre",
    "epreuve": "MI"
  },
  {
    "id": "D147062437",
    "nom": "Aboutayeb",
    "prenom": "Ikram",
    "numero_examen": 1019,
    "salle_examen": "Amphitheatre",
    "epreuve": "MI"
  },
  {
    "id": "D130143820",
    "nom": "Achahrour",
    "prenom": "Mustapha",
    "numero_examen": 1020,
    "salle_examen": "Amphitheatre",
    "epreuve": "MI"
  },
  {
    "id": "D130260668",
    "nom": "Achane",
    "prenom": "Nezha",
    "numero_examen": 1021,
    "salle_examen": "Amphitheatre",
    "epreuve": "MI"
  },
  {
    "id": "D135288604",
    "nom": "Achhachar",
    "prenom": "Yassine",
    "numero_examen": 1022,
    "salle_examen": "Amphitheatre",
    "epreuve": "MI"
  },
  {
    "id": "G131439219",
    "nom": "Achlou",
    "prenom": "Anir",
    "numero_examen": 1023,
    "salle_examen": "Amphitheatre",
    "epreuve": "MI"
  },
  {
    "id": "G133499583",
    "nom": "Achouay",
    "prenom": "Abdelilah",
    "numero_examen": 1024,
    "salle_examen": "Amphitheatre",
    "epreuve": "MI"
  },
  {
    "id": "C131096632",
    "nom": "Adaaiche",
    "prenom": "Issalmou",
    "numero_examen": 1025,
    "salle_examen": "Amphitheatre",
    "epreuve": "MI"
  },
  {
    "id": "F135201084",
    "nom": "Adam",
    "prenom": "Moutik",
    "numero_examen": 1026,
    "salle_examen": "Amphitheatre",
    "epreuve": "MI"
  },
  {
    "id": "R132519575",
    "nom": "Afi",
    "prenom": "Samia",
    "numero_examen": 1027,
    "salle_examen": "Amphitheatre",
    "epreuve": "MI"
  },
  {
    "id": "R133938161",
    "nom": "Afkir",
    "prenom": "Chaimaa",
    "numero_examen": 1028,
    "salle_examen": "Amphitheatre",
    "epreuve": "MI"
  },
  {
    "id": "R135417058",
    "nom": "Agazzara",
    "prenom": "Keltoum",
    "numero_examen": 1029,
    "salle_examen": "Amphitheatre",
    "epreuve": "MI"
  },
  {
    "id": "E137002903",
    "nom": "Aghbalou",
    "prenom": "Driss",
    "numero_examen": 1030,
    "salle_examen": "Amphitheatre",
    "epreuve": "MI"
  },
  {
    "id": "J134242423",
    "nom": "Agouzoul",
    "prenom": "Naima",
    "numero_examen": 1031,
    "salle_examen": "Amphitheatre",
    "epreuve": "MI"
  },
  {
    "id": "M139193916",
    "nom": "Agrat",
    "prenom": "El Mehdi",
    "numero_examen": 1032,
    "salle_examen": "Amphitheatre",
    "epreuve": "MI"
  },
  {
    "id": "J131166478",
    "nom": "Agrou",
    "prenom": "Abdelali",
    "numero_examen": 1033,
    "salle_examen": "Amphitheatre",
    "epreuve": "MI"
  },
  {
    "id": "G138288104",
    "nom": "Ahachmi",
    "prenom": "Fadoua",
    "numero_examen": 1034,
    "salle_examen": "Amphitheatre",
    "epreuve": "MI"
  },
  {
    "id": "S136055355",
    "nom": "Ahaggach",
    "prenom": "Kaoutar",
    "numero_examen": 1035,
    "salle_examen": "Amphitheatre",
    "epreuve": "MI"
  },
  {
    "id": "D130409396",
    "nom": "Ahanou",
    "prenom": "Ayoub",
    "numero_examen": 1036,
    "salle_examen": "Amphitheatre",
    "epreuve": "MI"
  },
  {
    "id": "S133227868",
    "nom": "Ahethour",
    "prenom": "Nihad",
    "numero_examen": 1037,
    "salle_examen": "Amphitheatre",
    "epreuve": "MI"
  },
  {
    "id": "D120021290",
    "nom": "Ahouari",
    "prenom": "Mohamed",
    "numero_examen": 1038,
    "salle_examen": "Amphitheatre",
    "epreuve": "MI"
  },
  {
    "id": "G139342674",
    "nom": "Ait Allal",
    "prenom": "Mohammed",
    "numero_examen": 1039,
    "salle_examen": "Amphitheatre",
    "epreuve": "MI"
  },
  {
    "id": "R130130999",
    "nom": "Ait Baba Hida",
    "prenom": "Fatima Zahra",
    "numero_examen": 1040,
    "salle_examen": "Amphitheatre",
    "epreuve": "MI"
  },
  {
    "id": "D136528180",
    "nom": "Ait Bouhou",
    "prenom": "Hamza",
    "numero_examen": 1041,
    "salle_examen": "Amphitheatre",
    "epreuve": "MI"
  },
  {
    "id": "R131437426",
    "nom": "Ait Cheikh",
    "prenom": "Ilyass",
    "numero_examen": 1042,
    "salle_examen": "Amphitheatre",
    "epreuve": "MI"
  },
  {
    "id": "D137513702",
    "nom": "Ait El Kadi",
    "prenom": "Mohamed",
    "numero_examen": 1043,
    "salle_examen": "Amphitheatre",
    "epreuve": "MI"
  },
  {
    "id": "R137233681",
    "nom": "Ait Elmaalem",
    "prenom": "Siham",
    "numero_examen": 1044,
    "salle_examen": "Amphitheatre",
    "epreuve": "MI"
  },
  {
    "id": "D139498034",
    "nom": "Ait Hmane",
    "prenom": "Ihssane",
    "numero_examen": 1045,
    "salle_examen": "Amphitheatre",
    "epreuve": "MI"
  },
  {
    "id": "Z175100051",
    "nom": "Ait Hmane",
    "prenom": "Zakaria",
    "numero_examen": 1046,
    "salle_examen": "Amphitheatre",
    "epreuve": "MI"
  },
  {
    "id": "R130697294",
    "nom": "Ait Lahcen",
    "prenom": "Khadija",
    "numero_examen": 1047,
    "salle_examen": "Amphitheatre",
    "epreuve": "MI"
  },
  {
    "id": "D130879463",
    "nom": "Ait Yahia",
    "prenom": "Layla",
    "numero_examen": 1048,
    "salle_examen": "Amphitheatre",
    "epreuve": "MI"
  },
  {
    "id": "D136548800",
    "nom": "Akharraz",
    "prenom": "Asma",
    "numero_examen": 1049,
    "salle_examen": "Amphitheatre",
    "epreuve": "MI"
  },
  {
    "id": "F132113403",
    "nom": "Akhouad",
    "prenom": "Salma",
    "numero_examen": 1050,
    "salle_examen": "Amphitheatre",
    "epreuve": "MI"
  },
  {
    "id": "D132745334",
    "nom": "Akhouairi",
    "prenom": "Hamza",
    "numero_examen": 1051,
    "salle_examen": "Amphitheatre",
    "epreuve": "MI"
  },
  {
    "id": "R138454925",
    "nom": "Akioud",
    "prenom": "Rayan",
    "numero_examen": 1052,
    "salle_examen": "Amphitheatre",
    "epreuve": "MI"
  },
  {
    "id": "D110023830",
    "nom": "Akka",
    "prenom": "Abdelilah",
    "numero_examen": 1053,
    "salle_examen": "Amphitheatre",
    "epreuve": "MI"
  },
  {
    "id": "M134489716",
    "nom": "Akniz",
    "prenom": "Fatima Ezzahrae",
    "numero_examen": 1054,
    "salle_examen": "Amphitheatre",
    "epreuve": "MI"
  },
  {
    "id": "G130540918",
    "nom": "Akram",
    "prenom": "Ahlam",
    "numero_examen": 1055,
    "salle_examen": "Amphitheatre",
    "epreuve": "MI"
  },
  {
    "id": "D131340950",
    "nom": "Al Rhafari",
    "prenom": "Hiba",
    "numero_examen": 1056,
    "salle_examen": "Amphitheatre",
    "epreuve": "MI"
  },
  {
    "id": "D131287203",
    "nom": "Alahiane",
    "prenom": "Said",
    "numero_examen": 1057,
    "salle_examen": "Amphitheatre",
    "epreuve": "MI"
  },
  {
    "id": "D130226354",
    "nom": "Alahyane",
    "prenom": "Youssef",
    "numero_examen": 1058,
    "salle_examen": "Amphitheatre",
    "epreuve": "MI"
  },
  {
    "id": "M135265065",
    "nom": "Alala",
    "prenom": "Mohamed",
    "numero_examen": 1059,
    "salle_examen": "Amphitheatre",
    "epreuve": "MI"
  },
  {
    "id": "R131531224",
    "nom": "Alami",
    "prenom": "Yassine",
    "numero_examen": 1060,
    "salle_examen": "Amphitheatre",
    "epreuve": "MI"
  },
  {
    "id": "S135389400",
    "nom": "Allaoui",
    "prenom": "Imane",
    "numero_examen": 1061,
    "salle_examen": "Amphitheatre",
    "epreuve": "MI"
  },
  {
    "id": "G132492896",
    "nom": "Alyachiri",
    "prenom": "Aimrane",
    "numero_examen": 1062,
    "salle_examen": "Amphitheatre",
    "epreuve": "MI"
  },
  {
    "id": "R130540238",
    "nom": "Amalal",
    "prenom": "Oumnia",
    "numero_examen": 1063,
    "salle_examen": "Amphitheatre",
    "epreuve": "MI"
  },
  {
    "id": "R133434179",
    "nom": "Amine",
    "prenom": "Hiba",
    "numero_examen": 1064,
    "salle_examen": "Amphitheatre",
    "epreuve": "MI"
  },
  {
    "id": "R130047036",
    "nom": "Amiqadir",
    "prenom": "Ouissal",
    "numero_examen": 1065,
    "salle_examen": "Amphitheatre",
    "epreuve": "MI"
  },
  {
    "id": "M120048614",
    "nom": "Amraoui",
    "prenom": "Souaad",
    "numero_examen": 1066,
    "salle_examen": "Amphitheatre",
    "epreuve": "MI"
  },
  {
    "id": "X231060199",
    "nom": "Anani",
    "prenom": "Mawoueyram",
    "numero_examen": 1067,
    "salle_examen": "Amphitheatre",
    "epreuve": "MI"
  },
  {
    "id": "D131375892",
    "nom": "Anaou",
    "prenom": "Lina",
    "numero_examen": 1068,
    "salle_examen": "Amphitheatre",
    "epreuve": "MI"
  },
  {
    "id": "ESTO230704",
    "nom": "Andral",
    "prenom": "Be Christopher",
    "numero_examen": 1069,
    "salle_examen": "Amphitheatre",
    "epreuve": "MI"
  },
  {
    "id": "G139397163",
    "nom": "Aqbadou",
    "prenom": "Othmane",
    "numero_examen": 1070,
    "salle_examen": "Amphitheatre",
    "epreuve": "MI"
  },
  {
    "id": "R132418992",
    "nom": "Araich",
    "prenom": "Mohamed Amine",
    "numero_examen": 1071,
    "salle_examen": "Amphitheatre",
    "epreuve": "MI"
  },
  {
    "id": "R130589233",
    "nom": "Araour",
    "prenom": "Ammar",
    "numero_examen": 1072,
    "salle_examen": "Amphitheatre",
    "epreuve": "MI"
  },
  {
    "id": "B135071195",
    "nom": "Arbia",
    "prenom": "Hani",
    "numero_examen": 1073,
    "salle_examen": "Amphitheatre",
    "epreuve": "MI"
  },
  {
    "id": "M130372039",
    "nom": "Arharbi",
    "prenom": "Latifa",
    "numero_examen": 1074,
    "salle_examen": "Amphitheatre",
    "epreuve": "MI"
  },
  {
    "id": "K138214516",
    "nom": "Assaf",
    "prenom": "Aya",
    "numero_examen": 1075,
    "salle_examen": "Amphitheatre",
    "epreuve": "MI"
  },
  {
    "id": "R130412910",
    "nom": "Assaffah",
    "prenom": "Malak",
    "numero_examen": 1076,
    "salle_examen": "Amphitheatre",
    "epreuve": "MI"
  },
  {
    "id": "R132928287",
    "nom": "Assil",
    "prenom": "Sara",
    "numero_examen": 1077,
    "salle_examen": "Amphitheatre",
    "epreuve": "MI"
  },
  {
    "id": "R130110275",
    "nom": "Atila",
    "prenom": "Hammam",
    "numero_examen": 1078,
    "salle_examen": "Amphitheatre",
    "epreuve": "MI"
  },
  {
    "id": "R136300009",
    "nom": "Atiq",
    "prenom": "Mohammed",
    "numero_examen": 1079,
    "salle_examen": "Amphitheatre",
    "epreuve": "MI"
  },
  {
    "id": "D135225045",
    "nom": "Atouf",
    "prenom": "Kaoutar",
    "numero_examen": 1080,
    "salle_examen": "Amphitheatre",
    "epreuve": "MI"
  },
  {
    "id": "D133519522",
    "nom": "Ayoubi",
    "prenom": "Yassine",
    "numero_examen": 1081,
    "salle_examen": "Amphitheatre",
    "epreuve": "MI"
  },
  {
    "id": "R136537230",
    "nom": "Azaouaghe",
    "prenom": "Mohamed Amine",
    "numero_examen": 1082,
    "salle_examen": "Amphitheatre",
    "epreuve": "MI"
  },
  {
    "id": "E140196962",
    "nom": "Azarou",
    "prenom": "Lamiae",
    "numero_examen": 1083,
    "salle_examen": "Amphitheatre",
    "epreuve": "MI"
  },
  {
    "id": "D131366414",
    "nom": "Azatouri",
    "prenom": "Rabya",
    "numero_examen": 1084,
    "salle_examen": "Amphitheatre",
    "epreuve": "MI"
  },
  {
    "id": "L137115074",
    "nom": "Azelag",
    "prenom": "Abdelhakim",
    "numero_examen": 1085,
    "salle_examen": "Amphitheatre",
    "epreuve": "MI"
  },
  {
    "id": "H130000022",
    "nom": "Aziz",
    "prenom": "Aymane",
    "numero_examen": 1086,
    "salle_examen": "Amphitheatre",
    "epreuve": "MI"
  },
  {
    "id": "H133096492",
    "nom": "Azizi",
    "prenom": "Abdelilah",
    "numero_examen": 1087,
    "salle_examen": "Amphitheatre",
    "epreuve": "MI"
  },
  {
    "id": "D131193008",
    "nom": "Azizi",
    "prenom": "Simane",
    "numero_examen": 1088,
    "salle_examen": "Amphitheatre",
    "epreuve": "MI"
  },
  {
    "id": "R130171039",
    "nom": "Baaiza",
    "prenom": "Walid",
    "numero_examen": 1089,
    "salle_examen": "Amphitheatre",
    "epreuve": "MI"
  },
  {
    "id": "M139318792",
    "nom": "Badaoui",
    "prenom": "Mohammed",
    "numero_examen": 1090,
    "salle_examen": "Amphitheatre",
    "epreuve": "MI"
  },
  {
    "id": "2392210006",
    "nom": "Bado",
    "prenom": "Yipene Ange Cenacle",
    "numero_examen": 1091,
    "salle_examen": "Amphitheatre",
    "epreuve": "MI"
  },
  {
    "id": "R130193627",
    "nom": "Baha",
    "prenom": "Nadia",
    "numero_examen": 1092,
    "salle_examen": "Amphitheatre",
    "epreuve": "MI"
  },
  {
    "id": "H131335025",
    "nom": "Bahassan",
    "prenom": "Lamiss",
    "numero_examen": 1093,
    "salle_examen": "Amphitheatre",
    "epreuve": "MI"
  },
  {
    "id": "J143049414",
    "nom": "Bahri",
    "prenom": "Ilhame",
    "numero_examen": 1094,
    "salle_examen": "Amphitheatre",
    "epreuve": "MI"
  },
  {
    "id": "B131072364",
    "nom": "Baicha",
    "prenom": "Mohamed",
    "numero_examen": 1095,
    "salle_examen": "Amphitheatre",
    "epreuve": "MI"
  },
  {
    "id": "J137406191",
    "nom": "Bakbachi",
    "prenom": "Amina",
    "numero_examen": 1096,
    "salle_examen": "Amphitheatre",
    "epreuve": "MI"
  },
  {
    "id": "N138321797",
    "nom": "Bakkara",
    "prenom": "Aya",
    "numero_examen": 1097,
    "salle_examen": "Amphitheatre",
    "epreuve": "MI"
  },
  {
    "id": "P134110852",
    "nom": "Bakkari",
    "prenom": "Zakariae",
    "numero_examen": 1098,
    "salle_examen": "Amphitheatre",
    "epreuve": "MI"
  },
  {
    "id": "D100050537",
    "nom": "Bakziz",
    "prenom": "Yahia",
    "numero_examen": 1099,
    "salle_examen": "Amphitheatre",
    "epreuve": "MI"
  },
  {
    "id": "B139036089",
    "nom": "Bamousa",
    "prenom": "Safa",
    "numero_examen": 1100,
    "salle_examen": "Amphitheatre",
    "epreuve": "MI"
  },
  {
    "id": "K134091033",
    "nom": "Banani",
    "prenom": "Halima",
    "numero_examen": 1101,
    "salle_examen": "Amphi1",
    "epreuve": "MI"
  },
  {
    "id": "R132283045",
    "nom": "Bani",
    "prenom": "Yasser",
    "numero_examen": 1102,
    "salle_examen": "Amphi1",
    "epreuve": "MI"
  },
  {
    "id": "G133774408",
    "nom": "Barkhioui",
    "prenom": "Anas",
    "numero_examen": 1103,
    "salle_examen": "Amphi1",
    "epreuve": "MI"
  },
  {
    "id": "R138687531",
    "nom": "Baroudi",
    "prenom": "Yassine",
    "numero_examen": 1104,
    "salle_examen": "Amphi1",
    "epreuve": "MI"
  },
  {
    "id": "R120053630",
    "nom": "Bartine",
    "prenom": "Hiba",
    "numero_examen": 1105,
    "salle_examen": "Amphi1",
    "epreuve": "MI"
  },
  {
    "id": "J138536954",
    "nom": "Belachqer",
    "prenom": "Nada",
    "numero_examen": 1106,
    "salle_examen": "Amphi1",
    "epreuve": "MI"
  },
  {
    "id": "R132463001",
    "nom": "Belazri",
    "prenom": "Hamza",
    "numero_examen": 1107,
    "salle_examen": "Amphi1",
    "epreuve": "MI"
  },
  {
    "id": "E202328005",
    "nom": "Belemsigri",
    "prenom": "Windyam Juste Yannel",
    "numero_examen": 1108,
    "salle_examen": "Amphi1",
    "epreuve": "MI"
  },
  {
    "id": "K132213852",
    "nom": "Belhaimoudia",
    "prenom": "Zaynab",
    "numero_examen": 1109,
    "salle_examen": "Amphi1",
    "epreuve": "MI"
  },
  {
    "id": "J100050501",
    "nom": "Belhous",
    "prenom": "Adam",
    "numero_examen": 1110,
    "salle_examen": "Amphi1",
    "epreuve": "MI"
  },
  {
    "id": "H134233363",
    "nom": "Belkadi",
    "prenom": "Abderrahmane",
    "numero_examen": 1111,
    "salle_examen": "Amphi1",
    "epreuve": "MI"
  },
  {
    "id": "R130189361",
    "nom": "Belkaid",
    "prenom": "Meriem",
    "numero_examen": 1112,
    "salle_examen": "Amphi1",
    "epreuve": "MI"
  },
  {
    "id": "L134051370",
    "nom": "Belkhair",
    "prenom": "Otmane",
    "numero_examen": 1113,
    "salle_examen": "Amphi1",
    "epreuve": "MI"
  },
  {
    "id": "H132267849",
    "nom": "Belkhir",
    "prenom": "Chaymae",
    "numero_examen": 1114,
    "salle_examen": "Amphi1",
    "epreuve": "MI"
  },
  {
    "id": "R130047644",
    "nom": "Belkhiri",
    "prenom": "Hiba",
    "numero_examen": 1115,
    "salle_examen": "Amphi1",
    "epreuve": "MI"
  },
  {
    "id": "G139241841.",
    "nom": "Bellakhadim",
    "prenom": "Bouchra",
    "numero_examen": 1116,
    "salle_examen": "Amphi1",
    "epreuve": "MI"
  },
  {
    "id": "D136272814",
    "nom": "Bellouch",
    "prenom": "Walid",
    "numero_examen": 1117,
    "salle_examen": "Amphi1",
    "epreuve": "MI"
  },
  {
    "id": "D131430374",
    "nom": "Ben Birouk",
    "prenom": "Hassan",
    "numero_examen": 1118,
    "salle_examen": "Amphi1",
    "epreuve": "MI"
  },
  {
    "id": "G130636095",
    "nom": "Ben Driouich",
    "prenom": "Hiba",
    "numero_examen": 1119,
    "salle_examen": "Amphi1",
    "epreuve": "MI"
  },
  {
    "id": "G135188598",
    "nom": "Ben Haida",
    "prenom": "Khadija",
    "numero_examen": 1120,
    "salle_examen": "Amphi1",
    "epreuve": "MI"
  },
  {
    "id": "J138211655",
    "nom": "Ben Hassoun",
    "prenom": "Asmae",
    "numero_examen": 1121,
    "salle_examen": "Amphi1",
    "epreuve": "MI"
  },
  {
    "id": "J130011856",
    "nom": "Benabbou",
    "prenom": "Reda",
    "numero_examen": 1122,
    "salle_examen": "Amphi1",
    "epreuve": "MI"
  },
  {
    "id": "H134347665",
    "nom": "Benaissa",
    "prenom": "Anouar",
    "numero_examen": 1123,
    "salle_examen": "Amphi1",
    "epreuve": "MI"
  },
  {
    "id": "R138898824",
    "nom": "Benhadar",
    "prenom": "Mohamed",
    "numero_examen": 1124,
    "salle_examen": "Amphi1",
    "epreuve": "MI"
  },
  {
    "id": "G135097431",
    "nom": "Benjabar",
    "prenom": "Chaimae",
    "numero_examen": 1125,
    "salle_examen": "Amphi1",
    "epreuve": "MI"
  },
  {
    "id": "J143061074",
    "nom": "Benjelloun",
    "prenom": "Oussama",
    "numero_examen": 1126,
    "salle_examen": "Amphi1",
    "epreuve": "MI"
  },
  {
    "id": "J130053483",
    "nom": "Benkhay",
    "prenom": "Othmane",
    "numero_examen": 1127,
    "salle_examen": "Amphi1",
    "epreuve": "MI"
  },
  {
    "id": "F137047791",
    "nom": "Benlabbiji",
    "prenom": "Fadoua",
    "numero_examen": 1128,
    "salle_examen": "Amphi1",
    "epreuve": "MI"
  },
  {
    "id": "R132465414",
    "nom": "Benmakia",
    "prenom": "Salma",
    "numero_examen": 1129,
    "salle_examen": "Amphi1",
    "epreuve": "MI"
  },
  {
    "id": "H130026303",
    "nom": "Benmoumen",
    "prenom": "Taha",
    "numero_examen": 1130,
    "salle_examen": "Amphi1",
    "epreuve": "MI"
  },
  {
    "id": "G148030335",
    "nom": "Benseddiq",
    "prenom": "Soufiane",
    "numero_examen": 1131,
    "salle_examen": "Amphi1",
    "epreuve": "MI"
  },
  {
    "id": "H136096498",
    "nom": "Benyamna",
    "prenom": "Mohammed",
    "numero_examen": 1132,
    "salle_examen": "Amphi1",
    "epreuve": "MI"
  },
  {
    "id": "F135114534",
    "nom": "Berrouyne",
    "prenom": "Malak",
    "numero_examen": 1133,
    "salle_examen": "Amphi1",
    "epreuve": "MI"
  },
  {
    "id": "D134724381",
    "nom": "Bhija",
    "prenom": "Samira",
    "numero_examen": 1134,
    "salle_examen": "Amphi1",
    "epreuve": "MI"
  },
  {
    "id": "ESTO090805",
    "nom": "Biakginbo Ahmadou Saly",
    "prenom": "Aristide",
    "numero_examen": 1135,
    "salle_examen": "Amphi1",
    "epreuve": "MI"
  },
  {
    "id": "R141122377",
    "nom": "Bilal",
    "prenom": "Wafae",
    "numero_examen": 1136,
    "salle_examen": "Amphi1",
    "epreuve": "MI"
  },
  {
    "id": "2300050042",
    "nom": "Bogre",
    "prenom": "Azimatou Ariane",
    "numero_examen": 1137,
    "salle_examen": "Amphi1",
    "epreuve": "MI"
  },
  {
    "id": "K132333883",
    "nom": "Bordo",
    "prenom": "Imane",
    "numero_examen": 1138,
    "salle_examen": "Amphi1",
    "epreuve": "MI"
  },
  {
    "id": "G131027575",
    "nom": "Bouaali",
    "prenom": "Fouad",
    "numero_examen": 1139,
    "salle_examen": "Amphi1",
    "epreuve": "MI"
  },
  {
    "id": "H138119113",
    "nom": "Bouakline",
    "prenom": "Oumayma",
    "numero_examen": 1140,
    "salle_examen": "Amphi1",
    "epreuve": "MI"
  },
  {
    "id": "M140064296",
    "nom": "Bouali",
    "prenom": "Imane",
    "numero_examen": 1141,
    "salle_examen": "Amphi2",
    "epreuve": "MI"
  },
  {
    "id": "M131223529",
    "nom": "Bouali",
    "prenom": "Younes",
    "numero_examen": 1142,
    "salle_examen": "Amphi2",
    "epreuve": "MI"
  },
  {
    "id": "G139382566",
    "nom": "Bouanani",
    "prenom": "Abderrahman",
    "numero_examen": 1143,
    "salle_examen": "Amphi2",
    "epreuve": "MI"
  },
  {
    "id": "V385912",
    "nom": "Boubrik",
    "prenom": "Aissam",
    "numero_examen": 1144,
    "salle_examen": "Amphi2",
    "epreuve": "MI"
  },
  {
    "id": "2005020200262",
    "nom": "Bouchantouf",
    "prenom": "Imane",
    "numero_examen": 1145,
    "salle_examen": "Amphi2",
    "epreuve": "MI"
  },
  {
    "id": "D144000077",
    "nom": "Boudghar",
    "prenom": "Oualid",
    "numero_examen": 1146,
    "salle_examen": "Amphi2",
    "epreuve": "MI"
  },
  {
    "id": "S136080070",
    "nom": "Bougarne",
    "prenom": "Amine",
    "numero_examen": 1147,
    "salle_examen": "Amphi2",
    "epreuve": "MI"
  },
  {
    "id": "B131078507",
    "nom": "Boughariyoune",
    "prenom": "Ahmed",
    "numero_examen": 1148,
    "salle_examen": "Amphi2",
    "epreuve": "MI"
  },
  {
    "id": "M130120991",
    "nom": "Bouhaddach",
    "prenom": "Omar",
    "numero_examen": 1149,
    "salle_examen": "Amphi2",
    "epreuve": "MI"
  },
  {
    "id": "F130269200",
    "nom": "Bouhlal",
    "prenom": "Hicham",
    "numero_examen": 1150,
    "salle_examen": "Amphi2",
    "epreuve": "MI"
  },
  {
    "id": "R131382136",
    "nom": "Bouhlaoui",
    "prenom": "Aymane",
    "numero_examen": 1151,
    "salle_examen": "Amphi2",
    "epreuve": "MI"
  },
  {
    "id": "G132214640",
    "nom": "Bouhouch",
    "prenom": "Jamal",
    "numero_examen": 1152,
    "salle_examen": "Amphi2",
    "epreuve": "MI"
  },
  {
    "id": "G132552502",
    "nom": "Bouhsine",
    "prenom": "El Houssein",
    "numero_examen": 1153,
    "salle_examen": "Amphi2",
    "epreuve": "MI"
  },
  {
    "id": "J100017597",
    "nom": "Bouita",
    "prenom": "Yassir",
    "numero_examen": 1154,
    "salle_examen": "Amphi2",
    "epreuve": "MI"
  },
  {
    "id": "G131709440",
    "nom": "Bouitane",
    "prenom": "Sara",
    "numero_examen": 1155,
    "salle_examen": "Amphi2",
    "epreuve": "MI"
  },
  {
    "id": "F138346005",
    "nom": "Boujay",
    "prenom": "Ilyas",
    "numero_examen": 1156,
    "salle_examen": "Amphi2",
    "epreuve": "MI"
  },
  {
    "id": "G130494796",
    "nom": "Boukhlal",
    "prenom": "Fatima Ezzahra",
    "numero_examen": 1157,
    "salle_examen": "Amphi2",
    "epreuve": "MI"
  },
  {
    "id": "G137245287",
    "nom": "Boulaarab",
    "prenom": "Othmane",
    "numero_examen": 1158,
    "salle_examen": "Amphi2",
    "epreuve": "MI"
  },
  {
    "id": "R130188873",
    "nom": "Bouloul",
    "prenom": "Rida",
    "numero_examen": 1159,
    "salle_examen": "Amphi2",
    "epreuve": "MI"
  },
  {
    "id": "D137632522",
    "nom": "Bouougrou",
    "prenom": "Yassin",
    "numero_examen": 1160,
    "salle_examen": "Amphi2",
    "epreuve": "MI"
  },
  {
    "id": "D132188438",
    "nom": "Bouqelall",
    "prenom": "Soufiane",
    "numero_examen": 1161,
    "salle_examen": "Amphi2",
    "epreuve": "MI"
  },
  {
    "id": "F147078009",
    "nom": "Bouraqba",
    "prenom": "Nizar",
    "numero_examen": 1162,
    "salle_examen": "Amphi2",
    "epreuve": "MI"
  },
  {
    "id": "R134871016",
    "nom": "Bouras",
    "prenom": "Mouad",
    "numero_examen": 1163,
    "salle_examen": "Amphi2",
    "epreuve": "MI"
  },
  {
    "id": "M140065741",
    "nom": "Bourzigui",
    "prenom": "Ilyasse",
    "numero_examen": 1164,
    "salle_examen": "Amphi2",
    "epreuve": "MI"
  },
  {
    "id": "G135695837",
    "nom": "Bousebbat",
    "prenom": "Kamal",
    "numero_examen": 1165,
    "salle_examen": "Amphi2",
    "epreuve": "MI"
  },
  {
    "id": "R139769975",
    "nom": "Bousserhane",
    "prenom": "Brahim",
    "numero_examen": 1166,
    "salle_examen": "Amphi2",
    "epreuve": "MI"
  },
  {
    "id": "M138187423",
    "nom": "Bouya",
    "prenom": "Aimad",
    "numero_examen": 1167,
    "salle_examen": "Amphi2",
    "epreuve": "MI"
  },
  {
    "id": "K120026576",
    "nom": "Bouzid",
    "prenom": "Hiba",
    "numero_examen": 1168,
    "salle_examen": "Amphi2",
    "epreuve": "MI"
  },
  {
    "id": "S137102009",
    "nom": "Chaaouan",
    "prenom": "Hanane",
    "numero_examen": 1169,
    "salle_examen": "Amphi2",
    "epreuve": "MI"
  },
  {
    "id": "G136154967",
    "nom": "Chakir",
    "prenom": "Khalid",
    "numero_examen": 1170,
    "salle_examen": "Amphi2",
    "epreuve": "MI"
  },
  {
    "id": "D131254504",
    "nom": "Chakour",
    "prenom": "Aya",
    "numero_examen": 1171,
    "salle_examen": "Amphi2",
    "epreuve": "MI"
  },
  {
    "id": "S132138467",
    "nom": "Chakroune",
    "prenom": "Lamyae",
    "numero_examen": 1172,
    "salle_examen": "Amphi2",
    "epreuve": "MI"
  },
  {
    "id": "10014579",
    "nom": "Chami",
    "prenom": "Ijlal",
    "numero_examen": 1173,
    "salle_examen": "Amphi2",
    "epreuve": "MI"
  },
  {
    "id": "R138553419",
    "nom": "Chaouri",
    "prenom": "Yassine",
    "numero_examen": 1174,
    "salle_examen": "Amphi2",
    "epreuve": "MI"
  },
  {
    "id": "E132017167",
    "nom": "Chaqyq",
    "prenom": "Salma",
    "numero_examen": 1175,
    "salle_examen": "Amphi2",
    "epreuve": "MI"
  },
  {
    "id": "C137162273",
    "nom": "Chargaoui",
    "prenom": "Zakaria",
    "numero_examen": 1176,
    "salle_examen": "Amphi2",
    "epreuve": "MI"
  },
  {
    "id": "F134279091",
    "nom": "Charrafi",
    "prenom": "Ayoub",
    "numero_examen": 1177,
    "salle_examen": "Amphi2",
    "epreuve": "MI"
  },
  {
    "id": "E133020522",
    "nom": "Chatar",
    "prenom": "Imane",
    "numero_examen": 1178,
    "salle_examen": "Amphi2",
    "epreuve": "MI"
  },
  {
    "id": "D136652419",
    "nom": "Chatit",
    "prenom": "Abdelaziz",
    "numero_examen": 1179,
    "salle_examen": "Amphi2",
    "epreuve": "MI"
  },
  {
    "id": "G136143211",
    "nom": "Chbati",
    "prenom": "Salma",
    "numero_examen": 1180,
    "salle_examen": "Amphi2",
    "epreuve": "MI"
  },
  {
    "id": "P134517033",
    "nom": "Chentouf",
    "prenom": "Soumaya",
    "numero_examen": 1181,
    "salle_examen": "Amphi3",
    "epreuve": "MI"
  },
  {
    "id": "H120002082",
    "nom": "Chihi",
    "prenom": "Mohammed",
    "numero_examen": 1182,
    "salle_examen": "Amphi3",
    "epreuve": "MI"
  },
  {
    "id": "G135135031",
    "nom": "Chikhaoui",
    "prenom": "Anass",
    "numero_examen": 1183,
    "salle_examen": "Amphi3",
    "epreuve": "MI"
  },
  {
    "id": "L147032919",
    "nom": "Chkarka",
    "prenom": "Mouhssine",
    "numero_examen": 1184,
    "salle_examen": "Amphi3",
    "epreuve": "MI"
  },
  {
    "id": "R140115089",
    "nom": "Chmarkh",
    "prenom": "Abderrahmane",
    "numero_examen": 1185,
    "salle_examen": "Amphi3",
    "epreuve": "MI"
  },
  {
    "id": "E147193011",
    "nom": "Chnina",
    "prenom": "Adam",
    "numero_examen": 1186,
    "salle_examen": "Amphi3",
    "epreuve": "MI"
  },
  {
    "id": "D139387075",
    "nom": "Choqayr",
    "prenom": "Nourddine",
    "numero_examen": 1187,
    "salle_examen": "Amphi3",
    "epreuve": "MI"
  },
  {
    "id": "P132297759",
    "nom": "Chrayah",
    "prenom": "Salma",
    "numero_examen": 1188,
    "salle_examen": "Amphi3",
    "epreuve": "MI"
  },
  {
    "id": "R131616676",
    "nom": "Chrinbou",
    "prenom": "Oulaya",
    "numero_examen": 1189,
    "salle_examen": "Amphi3",
    "epreuve": "MI"
  },
  {
    "id": "R134769311",
    "nom": "Daaif",
    "prenom": "Ali",
    "numero_examen": 1190,
    "salle_examen": "Amphi3",
    "epreuve": "MI"
  },
  {
    "id": "E132067647",
    "nom": "Dalhi",
    "prenom": "Khadija",
    "numero_examen": 1191,
    "salle_examen": "Amphi3",
    "epreuve": "MI"
  },
  {
    "id": "M132222072",
    "nom": "Dami",
    "prenom": "Sara",
    "numero_examen": 1192,
    "salle_examen": "Amphi3",
    "epreuve": "MI"
  },
  {
    "id": "H139079547",
    "nom": "Dani",
    "prenom": "Maryame",
    "numero_examen": 1193,
    "salle_examen": "Amphi3",
    "epreuve": "MI"
  },
  {
    "id": "R120025886",
    "nom": "Daou",
    "prenom": "Anas",
    "numero_examen": 1194,
    "salle_examen": "Amphi3",
    "epreuve": "MI"
  },
  {
    "id": "M131131416",
    "nom": "Daoudi",
    "prenom": "Hafsa",
    "numero_examen": 1195,
    "salle_examen": "Amphi3",
    "epreuve": "MI"
  },
  {
    "id": "F130179108",
    "nom": "Dari",
    "prenom": "Oumnia",
    "numero_examen": 1196,
    "salle_examen": "Amphi3",
    "epreuve": "MI"
  },
  {
    "id": "H140037593",
    "nom": "Derouich",
    "prenom": "Ahmed",
    "numero_examen": 1197,
    "salle_examen": "Amphi3",
    "epreuve": "MI"
  },
  {
    "id": "R139332692",
    "nom": "Dian",
    "prenom": "Aya",
    "numero_examen": 1198,
    "salle_examen": "Amphi3",
    "epreuve": "MI"
  },
  {
    "id": "R133332310",
    "nom": "Dian",
    "prenom": "Douaa",
    "numero_examen": 1199,
    "salle_examen": "Amphi3",
    "epreuve": "MI"
  },
  {
    "id": "D135694329",
    "nom": "Dmissi",
    "prenom": "Khadija",
    "numero_examen": 1200,
    "salle_examen": "Amphi3",
    "epreuve": "MI"
  },
  {
    "id": "E140087878",
    "nom": "Douaghri",
    "prenom": "Douae",
    "numero_examen": 1201,
    "salle_examen": "Amphi3",
    "epreuve": "MI"
  },
  {
    "id": "P139386641",
    "nom": "Doukkali",
    "prenom": "Chaimae",
    "numero_examen": 1202,
    "salle_examen": "Amphi3",
    "epreuve": "MI"
  },
  {
    "id": "S136145072",
    "nom": "Driouche",
    "prenom": "Mohamed",
    "numero_examen": 1203,
    "salle_examen": "Amphi3",
    "epreuve": "MI"
  },
  {
    "id": "R130174052",
    "nom": "Ech-Charqy",
    "prenom": "Ikram",
    "numero_examen": 1204,
    "salle_examen": "Amphi3",
    "epreuve": "MI"
  },
  {
    "id": "R134342612",
    "nom": "Echchnaoui",
    "prenom": "Nohaila",
    "numero_examen": 1205,
    "salle_examen": "Amphi3",
    "epreuve": "MI"
  },
  {
    "id": "H120009251",
    "nom": "Echibani",
    "prenom": "Nada",
    "numero_examen": 1206,
    "salle_examen": "Amphi3",
    "epreuve": "MI"
  },
  {
    "id": "L130304141",
    "nom": "Ed-Deryouch",
    "prenom": "Mohamed",
    "numero_examen": 1207,
    "salle_examen": "Amphi3",
    "epreuve": "MI"
  },
  {
    "id": "R137342818",
    "nom": "Eddiche",
    "prenom": "Maroua",
    "numero_examen": 1208,
    "salle_examen": "Amphi3",
    "epreuve": "MI"
  },
  {
    "id": "R130334089",
    "nom": "El Abbadi",
    "prenom": "Safae",
    "numero_examen": 1209,
    "salle_examen": "Amphi3",
    "epreuve": "MI"
  },
  {
    "id": "J130037704",
    "nom": "El Absi",
    "prenom": "Youness",
    "numero_examen": 1210,
    "salle_examen": "Amphi3",
    "epreuve": "MI"
  },
  {
    "id": "C139145825",
    "nom": "El Achgar",
    "prenom": "Omar",
    "numero_examen": 1211,
    "salle_examen": "Amphi3",
    "epreuve": "MI"
  },
  {
    "id": "G138146413",
    "nom": "El Addaou",
    "prenom": "Amal",
    "numero_examen": 1212,
    "salle_examen": "Amphi3",
    "epreuve": "MI"
  },
  {
    "id": "H135120205",
    "nom": "El Ahmadi",
    "prenom": "Ahmed Yassine",
    "numero_examen": 1213,
    "salle_examen": "Amphi3",
    "epreuve": "MI"
  },
  {
    "id": "D135156581",
    "nom": "El Amri",
    "prenom": "Maroua",
    "numero_examen": 1214,
    "salle_examen": "Amphi3",
    "epreuve": "MI"
  },
  {
    "id": "J131438029",
    "nom": "El Anaya",
    "prenom": "Othman",
    "numero_examen": 1215,
    "salle_examen": "Amphi3",
    "epreuve": "MI"
  },
  {
    "id": "F130127129",
    "nom": "El Arbaoui",
    "prenom": "Marouane",
    "numero_examen": 1216,
    "salle_examen": "Amphi3",
    "epreuve": "MI"
  },
  {
    "id": "M130005177",
    "nom": "El Atmani",
    "prenom": "Choayb",
    "numero_examen": 1217,
    "salle_examen": "Amphi3",
    "epreuve": "MI"
  },
  {
    "id": "R110024299",
    "nom": "El Attar",
    "prenom": "Hamza",
    "numero_examen": 1218,
    "salle_examen": "Amphi3",
    "epreuve": "MI"
  },
  {
    "id": "R137698483",
    "nom": "El Baadidi",
    "prenom": "Abdelmajid",
    "numero_examen": 1219,
    "salle_examen": "Amphi3",
    "epreuve": "MI"
  },
  {
    "id": "S133302601",
    "nom": "El Bachiri",
    "prenom": "Zouhir",
    "numero_examen": 1220,
    "salle_examen": "Amphi3",
    "epreuve": "MI"
  },
  {
    "id": "N132030908",
    "nom": "El Barodi",
    "prenom": "Imade",
    "numero_examen": 1221,
    "salle_examen": "Amphi4",
    "epreuve": "MI"
  },
  {
    "id": "F136115921",
    "nom": "El Basity",
    "prenom": "Achraf",
    "numero_examen": 1222,
    "salle_examen": "Amphi4",
    "epreuve": "MI"
  },
  {
    "id": "D137681093",
    "nom": "El Bouadani",
    "prenom": "Abderrahmane",
    "numero_examen": 1223,
    "salle_examen": "Amphi4",
    "epreuve": "MI"
  },
  {
    "id": "R147018079",
    "nom": "El Boubakri",
    "prenom": "Aya",
    "numero_examen": 1224,
    "salle_examen": "Amphi4",
    "epreuve": "MI"
  },
  {
    "id": "S132062058",
    "nom": "El Bouzrazi",
    "prenom": "Nabil",
    "numero_examen": 1225,
    "salle_examen": "Amphi4",
    "epreuve": "MI"
  },
  {
    "id": "D132368210",
    "nom": "El Farissi",
    "prenom": "Oussama",
    "numero_examen": 1226,
    "salle_examen": "Amphi4",
    "epreuve": "MI"
  },
  {
    "id": "D142068524",
    "nom": "El Fila",
    "prenom": "Mouad",
    "numero_examen": 1227,
    "salle_examen": "Amphi4",
    "epreuve": "MI"
  },
  {
    "id": "R135493723",
    "nom": "El Ghandoury",
    "prenom": "Khadija",
    "numero_examen": 1228,
    "salle_examen": "Amphi4",
    "epreuve": "MI"
  },
  {
    "id": "R136705270",
    "nom": "El Gharrasy",
    "prenom": "Wissal",
    "numero_examen": 1229,
    "salle_examen": "Amphi4",
    "epreuve": "MI"
  },
  {
    "id": "P138263227",
    "nom": "El Ghaze",
    "prenom": "Douae",
    "numero_examen": 1230,
    "salle_examen": "Amphi4",
    "epreuve": "MI"
  },
  {
    "id": "G135584308",
    "nom": "El Hachtar",
    "prenom": "Abdellatif",
    "numero_examen": 1231,
    "salle_examen": "Amphi4",
    "epreuve": "MI"
  },
  {
    "id": "M132290963",
    "nom": "El Haddad",
    "prenom": "Mohamed",
    "numero_examen": 1232,
    "salle_examen": "Amphi4",
    "epreuve": "MI"
  },
  {
    "id": "R137564915",
    "nom": "El Haddani",
    "prenom": "Hanae",
    "numero_examen": 1233,
    "salle_examen": "Amphi4",
    "epreuve": "MI"
  },
  {
    "id": "J130034529",
    "nom": "El Hafiane",
    "prenom": "Salma",
    "numero_examen": 1234,
    "salle_examen": "Amphi4",
    "epreuve": "MI"
  },
  {
    "id": "E143062543",
    "nom": "El Hafid",
    "prenom": "Maryam",
    "numero_examen": 1235,
    "salle_examen": "Amphi4",
    "epreuve": "MI"
  },
  {
    "id": "N130362292",
    "nom": "El Haik",
    "prenom": "Mohammed Amine",
    "numero_examen": 1236,
    "salle_examen": "Amphi4",
    "epreuve": "MI"
  },
  {
    "id": "S133055537",
    "nom": "El Hajjami",
    "prenom": "Adam",
    "numero_examen": 1237,
    "salle_examen": "Amphi4",
    "epreuve": "MI"
  },
  {
    "id": "D136729093",
    "nom": "El Hamidi",
    "prenom": "Khalid",
    "numero_examen": 1238,
    "salle_examen": "Amphi4",
    "epreuve": "MI"
  },
  {
    "id": "G133448692",
    "nom": "El Hanbali",
    "prenom": "Douha",
    "numero_examen": 1239,
    "salle_examen": "Amphi4",
    "epreuve": "MI"
  },
  {
    "id": "S137093470",
    "nom": "El Haouari",
    "prenom": "Mohamed Amine",
    "numero_examen": 1240,
    "salle_examen": "Amphi4",
    "epreuve": "MI"
  },
  {
    "id": "K130292185",
    "nom": "El Harmali",
    "prenom": "Mousaab",
    "numero_examen": 1241,
    "salle_examen": "Amphi4",
    "epreuve": "MI"
  },
  {
    "id": "R132269303",
    "nom": "El Jaafary",
    "prenom": "Wiam",
    "numero_examen": 1242,
    "salle_examen": "Amphi4",
    "epreuve": "MI"
  },
  {
    "id": "R134347324",
    "nom": "El Jabari",
    "prenom": "Hiba",
    "numero_examen": 1243,
    "salle_examen": "Amphi4",
    "epreuve": "MI"
  },
  {
    "id": "N120035276",
    "nom": "El Janati",
    "prenom": "Amal",
    "numero_examen": 1244,
    "salle_examen": "Amphi4",
    "epreuve": "MI"
  },
  {
    "id": "N137362776",
    "nom": "El Janati",
    "prenom": "Hiba",
    "numero_examen": 1245,
    "salle_examen": "Amphi4",
    "epreuve": "MI"
  },
  {
    "id": "G136064781",
    "nom": "El Jaouhary",
    "prenom": "Imane",
    "numero_examen": 1246,
    "salle_examen": "Amphi4",
    "epreuve": "MI"
  },
  {
    "id": "R139279257",
    "nom": "El Kamili",
    "prenom": "Hafsa",
    "numero_examen": 1247,
    "salle_examen": "Amphi4",
    "epreuve": "MI"
  },
  {
    "id": "R135315933",
    "nom": "El Karch",
    "prenom": "Hajar",
    "numero_examen": 1248,
    "salle_examen": "Amphi4",
    "epreuve": "MI"
  },
  {
    "id": "Y136012245",
    "nom": "El Karramsi",
    "prenom": "Yacine",
    "numero_examen": 1249,
    "salle_examen": "Amphi4",
    "epreuve": "MI"
  },
  {
    "id": "F149062802",
    "nom": "El Katali",
    "prenom": "Yassir",
    "numero_examen": 1250,
    "salle_examen": "Amphi4",
    "epreuve": "MI"
  },
  {
    "id": "H146046915",
    "nom": "El Khadir",
    "prenom": "Safouane",
    "numero_examen": 1251,
    "salle_examen": "Amphi4",
    "epreuve": "MI"
  },
  {
    "id": "G130779621",
    "nom": "El Khadir",
    "prenom": "Siham",
    "numero_examen": 1252,
    "salle_examen": "Amphi4",
    "epreuve": "MI"
  },
  {
    "id": "D137192800",
    "nom": "El Khddar",
    "prenom": "Aicha",
    "numero_examen": 1253,
    "salle_examen": "Amphi4",
    "epreuve": "MI"
  },
  {
    "id": "G134826508",
    "nom": "El Khorchi",
    "prenom": "Farah",
    "numero_examen": 1254,
    "salle_examen": "Amphi4",
    "epreuve": "MI"
  },
  {
    "id": "G139088426",
    "nom": "El Kilany",
    "prenom": "Leila",
    "numero_examen": 1255,
    "salle_examen": "Amphi4",
    "epreuve": "MI"
  },
  {
    "id": "D133196994",
    "nom": "El Mahfoudi",
    "prenom": "Habiba",
    "numero_examen": 1256,
    "salle_examen": "Amphi4",
    "epreuve": "MI"
  },
  {
    "id": "G137305602",
    "nom": "El Mandili",
    "prenom": "Salma",
    "numero_examen": 1257,
    "salle_examen": "Amphi4",
    "epreuve": "MI"
  },
  {
    "id": "R130838411",
    "nom": "El Mehdaoui",
    "prenom": "Chaimaa",
    "numero_examen": 1258,
    "salle_examen": "Amphi4",
    "epreuve": "MI"
  },
  {
    "id": "J135331479",
    "nom": "El Meziane",
    "prenom": "Marwa",
    "numero_examen": 1259,
    "salle_examen": "Amphi4",
    "epreuve": "MI"
  },
  {
    "id": "G139250667",
    "nom": "El Mhadder",
    "prenom": "Yahya",
    "numero_examen": 1260,
    "salle_examen": "Amphi4",
    "epreuve": "MI"
  },
  {
    "id": "J137140174",
    "nom": "El Mouden",
    "prenom": "Siham",
    "numero_examen": 1261,
    "salle_examen": "Amphi5",
    "epreuve": "MI"
  },
  {
    "id": "R138531456",
    "nom": "El Moujibi",
    "prenom": "Abdelhadi",
    "numero_examen": 1262,
    "salle_examen": "Amphi5",
    "epreuve": "MI"
  },
  {
    "id": "A134001997",
    "nom": "El Omari",
    "prenom": "Ayoub",
    "numero_examen": 1263,
    "salle_examen": "Amphi5",
    "epreuve": "MI"
  },
  {
    "id": "S138113524",
    "nom": "El Omari",
    "prenom": "Douae",
    "numero_examen": 1264,
    "salle_examen": "Amphi5",
    "epreuve": "MI"
  },
  {
    "id": "D131275815",
    "nom": "El Qadi",
    "prenom": "Mohamed",
    "numero_examen": 1265,
    "salle_examen": "Amphi5",
    "epreuve": "MI"
  },
  {
    "id": "G137592219",
    "nom": "El Qarfad",
    "prenom": "Asmaa",
    "numero_examen": 1266,
    "salle_examen": "Amphi5",
    "epreuve": "MI"
  },
  {
    "id": "N135317694",
    "nom": "El Yahyaoui",
    "prenom": "Boutaina",
    "numero_examen": 1267,
    "salle_examen": "Amphi5",
    "epreuve": "MI"
  },
  {
    "id": "B139052471",
    "nom": "Elaabbadi",
    "prenom": "Chaymae",
    "numero_examen": 1268,
    "salle_examen": "Amphi5",
    "epreuve": "MI"
  },
  {
    "id": "R130027738",
    "nom": "El-Amrani",
    "prenom": "Youssef",
    "numero_examen": 1269,
    "salle_examen": "Amphi5",
    "epreuve": "MI"
  },
  {
    "id": "R130026091",
    "nom": "Elassafry",
    "prenom": "Aya",
    "numero_examen": 1270,
    "salle_examen": "Amphi5",
    "epreuve": "MI"
  },
  {
    "id": "D135153488",
    "nom": "El-Azzaouy",
    "prenom": "Khadija",
    "numero_examen": 1271,
    "salle_examen": "Amphi5",
    "epreuve": "MI"
  },
  {
    "id": "M144066056",
    "nom": "Elbaroudi",
    "prenom": "Layla",
    "numero_examen": 1272,
    "salle_examen": "Amphi5",
    "epreuve": "MI"
  },
  {
    "id": "R138349378",
    "nom": "El-Baz",
    "prenom": "Wissal",
    "numero_examen": 1273,
    "salle_examen": "Amphi5",
    "epreuve": "MI"
  },
  {
    "id": "L131129948",
    "nom": "Elbouchir",
    "prenom": "Mohamed",
    "numero_examen": 1274,
    "salle_examen": "Amphi5",
    "epreuve": "MI"
  },
  {
    "id": "K172013016",
    "nom": "Elfarissi",
    "prenom": "Zineb",
    "numero_examen": 1275,
    "salle_examen": "Amphi5",
    "epreuve": "MI"
  },
  {
    "id": "A130013440",
    "nom": "Elfatmi",
    "prenom": "Maroua",
    "numero_examen": 1276,
    "salle_examen": "Amphi5",
    "epreuve": "MI"
  },
  {
    "id": "R130020326",
    "nom": "Elferrouni",
    "prenom": "Zakaria",
    "numero_examen": 1277,
    "salle_examen": "Amphi5",
    "epreuve": "MI"
  },
  {
    "id": "J100061110",
    "nom": "Elghouari",
    "prenom": "Youssef",
    "numero_examen": 1278,
    "salle_examen": "Amphi5",
    "epreuve": "MI"
  },
  {
    "id": "K130050426",
    "nom": "Elhaddad",
    "prenom": "Omar",
    "numero_examen": 1279,
    "salle_examen": "Amphi5",
    "epreuve": "MI"
  },
  {
    "id": "R147117696",
    "nom": "Elhadi",
    "prenom": "Btissam",
    "numero_examen": 1280,
    "salle_examen": "Amphi5",
    "epreuve": "MI"
  },
  {
    "id": "R148066469",
    "nom": "Elhagouchi",
    "prenom": "Karim",
    "numero_examen": 1281,
    "salle_examen": "Amphi5",
    "epreuve": "MI"
  },
  {
    "id": "G130497186",
    "nom": "Elhattab",
    "prenom": "Nada",
    "numero_examen": 1282,
    "salle_examen": "Amphi5",
    "epreuve": "MI"
  },
  {
    "id": "K136510329",
    "nom": "Elhiyani",
    "prenom": "Hanane",
    "numero_examen": 1283,
    "salle_examen": "Amphi5",
    "epreuve": "MI"
  },
  {
    "id": "D130530866",
    "nom": "Elidrissy",
    "prenom": "Imad",
    "numero_examen": 1284,
    "salle_examen": "Amphi5",
    "epreuve": "MI"
  },
  {
    "id": "K138247525",
    "nom": "Elkaddouri",
    "prenom": "Marwa",
    "numero_examen": 1285,
    "salle_examen": "Amphi5",
    "epreuve": "MI"
  },
  {
    "id": "J133150868",
    "nom": "Elkhayati",
    "prenom": "Bilal",
    "numero_examen": 1286,
    "salle_examen": "Amphi5",
    "epreuve": "MI"
  },
  {
    "id": "G130523739",
    "nom": "Elkimya",
    "prenom": "Marouane",
    "numero_examen": 1287,
    "salle_examen": "Amphi5",
    "epreuve": "MI"
  },
  {
    "id": "D134136557",
    "nom": "Ellouz",
    "prenom": "Youssef",
    "numero_examen": 1288,
    "salle_examen": "Amphi5",
    "epreuve": "MI"
  },
  {
    "id": "G132076660",
    "nom": "Elmahdani",
    "prenom": "Nisrine",
    "numero_examen": 1289,
    "salle_examen": "Amphi5",
    "epreuve": "MI"
  },
  {
    "id": "R135289322",
    "nom": "Elmahi",
    "prenom": "Wissal",
    "numero_examen": 1290,
    "salle_examen": "Amphi5",
    "epreuve": "MI"
  },
  {
    "id": "R149093475",
    "nom": "Elmaimouni",
    "prenom": "Mohamed",
    "numero_examen": 1291,
    "salle_examen": "Amphi5",
    "epreuve": "MI"
  },
  {
    "id": "D138070101",
    "nom": "Elmalki",
    "prenom": "Salma",
    "numero_examen": 1292,
    "salle_examen": "Amphi5",
    "epreuve": "MI"
  },
  {
    "id": "R110094976",
    "nom": "Elmannany",
    "prenom": "Aymen",
    "numero_examen": 1293,
    "salle_examen": "Amphi5",
    "epreuve": "MI"
  },
  {
    "id": "J130013934",
    "nom": "Elmaouardi",
    "prenom": "Hajar",
    "numero_examen": 1294,
    "salle_examen": "Amphi5",
    "epreuve": "MI"
  },
  {
    "id": "R130078628",
    "nom": "Elmazouny",
    "prenom": "Abdelghafour",
    "numero_examen": 1295,
    "salle_examen": "Amphi5",
    "epreuve": "MI"
  },
  {
    "id": "G130172641",
    "nom": "Elmyloudy",
    "prenom": "Soukaina",
    "numero_examen": 1296,
    "salle_examen": "Amphi5",
    "epreuve": "MI"
  },
  {
    "id": "G130734136",
    "nom": "Elouardy",
    "prenom": "Fatima Zahrae",
    "numero_examen": 1297,
    "salle_examen": "Amphi5",
    "epreuve": "MI"
  },
  {
    "id": "Z224500010",
    "nom": "Elouzi",
    "prenom": "Salmane",
    "numero_examen": 1298,
    "salle_examen": "Amphi5",
    "epreuve": "MI"
  },
  {
    "id": "R130142479",
    "nom": "Ennair",
    "prenom": "Amal",
    "numero_examen": 1299,
    "salle_examen": "Amphi5",
    "epreuve": "MI"
  },
  {
    "id": "R138876080",
    "nom": "Ennaji",
    "prenom": "Aymen",
    "numero_examen": 1300,
    "salle_examen": "Amphi5",
    "epreuve": "MI"
  },
  {
    "id": "F165128739",
    "nom": "Ennassiri",
    "prenom": "Imad",
    "numero_examen": 1301,
    "salle_examen": "salle1",
    "epreuve": "MI"
  },
  {
    "id": "B138030609",
    "nom": "Er-Gaibi",
    "prenom": "El Mehdi",
    "numero_examen": 1302,
    "salle_examen": "salle1",
    "epreuve": "MI"
  },
  {
    "id": "P132083761",
    "nom": "Erouihi",
    "prenom": "Nouhad",
    "numero_examen": 1303,
    "salle_examen": "salle1",
    "epreuve": "MI"
  },
  {
    "id": "D135092810",
    "nom": "Errachidi",
    "prenom": "Douae",
    "numero_examen": 1304,
    "salle_examen": "salle1",
    "epreuve": "MI"
  },
  {
    "id": "R110169337",
    "nom": "Erradi",
    "prenom": "Zouhair",
    "numero_examen": 1305,
    "salle_examen": "salle1",
    "epreuve": "MI"
  },
  {
    "id": "M137213250",
    "nom": "Errafi",
    "prenom": "Imrane",
    "numero_examen": 1306,
    "salle_examen": "salle1",
    "epreuve": "MI"
  },
  {
    "id": "R120042485",
    "nom": "Er-Raqi",
    "prenom": "Fatima Zahrae",
    "numero_examen": 1307,
    "salle_examen": "salle1",
    "epreuve": "MI"
  },
  {
    "id": "C130003668",
    "nom": "Essabiri",
    "prenom": "Anouar",
    "numero_examen": 1308,
    "salle_examen": "salle1",
    "epreuve": "MI"
  },
  {
    "id": "R132598828",
    "nom": "Essamhi",
    "prenom": "Mohammed Amine",
    "numero_examen": 1309,
    "salle_examen": "salle1",
    "epreuve": "MI"
  },
  {
    "id": "F133038789",
    "nom": "Essoktani",
    "prenom": "Yazid",
    "numero_examen": 1310,
    "salle_examen": "salle1",
    "epreuve": "MI"
  },
  {
    "id": "R133580182",
    "nom": "Essossi El Alaoui",
    "prenom": "Asmaa",
    "numero_examen": 1311,
    "salle_examen": "salle1",
    "epreuve": "MI"
  },
  {
    "id": "R130161417",
    "nom": "Ettamri",
    "prenom": "Naoufel",
    "numero_examen": 1312,
    "salle_examen": "salle1",
    "epreuve": "MI"
  },
  {
    "id": "F132111332",
    "nom": "Ezzaher",
    "prenom": "Firdaousse",
    "numero_examen": 1313,
    "salle_examen": "salle1",
    "epreuve": "MI"
  },
  {
    "id": "R135418716",
    "nom": "Ez-Zahery",
    "prenom": "Ahmed Amine",
    "numero_examen": 1314,
    "salle_examen": "salle1",
    "epreuve": "MI"
  },
  {
    "id": "R130064364",
    "nom": "Ezzine",
    "prenom": "Hajar",
    "numero_examen": 1315,
    "salle_examen": "salle1",
    "epreuve": "MI"
  },
  {
    "id": "D133274251",
    "nom": "Fadil",
    "prenom": "Sara",
    "numero_examen": 1316,
    "salle_examen": "salle1",
    "epreuve": "MI"
  },
  {
    "id": "R130339132",
    "nom": "Fadry",
    "prenom": "Rania",
    "numero_examen": 1317,
    "salle_examen": "salle1",
    "epreuve": "MI"
  },
  {
    "id": "D134255254",
    "nom": "Faiz",
    "prenom": "Adnane",
    "numero_examen": 1318,
    "salle_examen": "salle1",
    "epreuve": "MI"
  },
  {
    "id": "F120014457",
    "nom": "Faouzi",
    "prenom": "Maryam",
    "numero_examen": 1319,
    "salle_examen": "salle1",
    "epreuve": "MI"
  },
  {
    "id": "R131220788",
    "nom": "Farkou",
    "prenom": "Oumaima",
    "numero_examen": 1320,
    "salle_examen": "salle1",
    "epreuve": "MI"
  },
  {
    "id": "R133273728",
    "nom": "Fatahllah",
    "prenom": "El Mehdi",
    "numero_examen": 1321,
    "salle_examen": "salle1",
    "epreuve": "MI"
  },
  {
    "id": "K134479909",
    "nom": "Fathi",
    "prenom": "Nisrine",
    "numero_examen": 1322,
    "salle_examen": "salle1",
    "epreuve": "MI"
  },
  {
    "id": "G134015429",
    "nom": "Fax",
    "prenom": "Charifa",
    "numero_examen": 1323,
    "salle_examen": "salle1",
    "epreuve": "MI"
  },
  {
    "id": "R136513635",
    "nom": "Fennane",
    "prenom": "Faisal",
    "numero_examen": 1324,
    "salle_examen": "salle1",
    "epreuve": "MI"
  },
  {
    "id": "R100123150",
    "nom": "Fezzaz",
    "prenom": "Imane",
    "numero_examen": 1325,
    "salle_examen": "salle1",
    "epreuve": "MI"
  },
  {
    "id": "F161091010",
    "nom": "Fliga",
    "prenom": "Yasmine",
    "numero_examen": 1326,
    "salle_examen": "salle1",
    "epreuve": "MI"
  },
  {
    "id": "D132098164",
    "nom": "Fouadi",
    "prenom": "Kaoutar",
    "numero_examen": 1327,
    "salle_examen": "salle1",
    "epreuve": "MI"
  },
  {
    "id": "D137545336",
    "nom": "Gdaa",
    "prenom": "Jabir",
    "numero_examen": 1328,
    "salle_examen": "salle1",
    "epreuve": "MI"
  },
  {
    "id": "F100070417",
    "nom": "Ghazi",
    "prenom": "Anas",
    "numero_examen": 1329,
    "salle_examen": "salle1",
    "epreuve": "MI"
  },
  {
    "id": "D138788321",
    "nom": "Ghiri",
    "prenom": "Houda",
    "numero_examen": 1330,
    "salle_examen": "salle1",
    "epreuve": "MI"
  },
  {
    "id": "R120042501",
    "nom": "Ghoufari",
    "prenom": "Sanaa",
    "numero_examen": 1331,
    "salle_examen": "salle1",
    "epreuve": "MI"
  },
  {
    "id": "D137130492",
    "nom": "Gounaine",
    "prenom": "Tahar",
    "numero_examen": 1332,
    "salle_examen": "salle1",
    "epreuve": "MI"
  },
  {
    "id": "H131201297",
    "nom": "Grouz",
    "prenom": "Yassmine",
    "numero_examen": 1333,
    "salle_examen": "salle1",
    "epreuve": "MI"
  },
  {
    "id": "R130110614",
    "nom": "Guarnaoui",
    "prenom": "Zakaria",
    "numero_examen": 1334,
    "salle_examen": "salle1",
    "epreuve": "MI"
  },
  {
    "id": "H130048069",
    "nom": "Habsi",
    "prenom": "Achraf",
    "numero_examen": 1335,
    "salle_examen": "salle1",
    "epreuve": "MI"
  },
  {
    "id": "E120025362",
    "nom": "Hachmoud",
    "prenom": "Soukaina",
    "numero_examen": 1336,
    "salle_examen": "salle1",
    "epreuve": "MI"
  },
  {
    "id": "Q369482",
    "nom": "Hadfani",
    "prenom": "Mohamed",
    "numero_examen": 1337,
    "salle_examen": "salle1",
    "epreuve": "MI"
  },
  {
    "id": "R130167649",
    "nom": "Hadi",
    "prenom": "Imane",
    "numero_examen": 1338,
    "salle_examen": "salle1",
    "epreuve": "MI"
  },
  {
    "id": "D139620890",
    "nom": "Hadidi",
    "prenom": "Ghizlane",
    "numero_examen": 1339,
    "salle_examen": "salle1",
    "epreuve": "MI"
  },
  {
    "id": "R139586877",
    "nom": "Hadir",
    "prenom": "Yahya",
    "numero_examen": 1340,
    "salle_examen": "salle1",
    "epreuve": "MI"
  },
  {
    "id": "H138090407",
    "nom": "Hadouch",
    "prenom": "Oussama",
    "numero_examen": 1341,
    "salle_examen": "salle1",
    "epreuve": "MI"
  },
  {
    "id": "M133232470",
    "nom": "Hafidi",
    "prenom": "Adam",
    "numero_examen": 1342,
    "salle_examen": "salle1",
    "epreuve": "MI"
  },
  {
    "id": "J131143333",
    "nom": "Hajji",
    "prenom": "Nasr-Eddine",
    "numero_examen": 1343,
    "salle_examen": "salle1",
    "epreuve": "MI"
  },
  {
    "id": "H120000978",
    "nom": "Hakkou",
    "prenom": "Wiame",
    "numero_examen": 1344,
    "salle_examen": "salle1",
    "epreuve": "MI"
  },
  {
    "id": "E120020577",
    "nom": "Hammou",
    "prenom": "Abdellah",
    "numero_examen": 1345,
    "salle_examen": "salle1",
    "epreuve": "MI"
  },
  {
    "id": "R139213327",
    "nom": "Hammou",
    "prenom": "Abderrahmane",
    "numero_examen": 1346,
    "salle_examen": "salle1",
    "epreuve": "MI"
  },
  {
    "id": "R130470084",
    "nom": "Hamouda",
    "prenom": "Jannate",
    "numero_examen": 1347,
    "salle_examen": "salle1",
    "epreuve": "MI"
  },
  {
    "id": "R136843943",
    "nom": "Hani",
    "prenom": "Anas",
    "numero_examen": 1348,
    "salle_examen": "salle1",
    "epreuve": "MI"
  },
  {
    "id": "D133323453",
    "nom": "Harbech",
    "prenom": "Mohamed",
    "numero_examen": 1349,
    "salle_examen": "salle1",
    "epreuve": "MI"
  },
  {
    "id": "R134551175",
    "nom": "Harhouri",
    "prenom": "Oumaima",
    "numero_examen": 1350,
    "salle_examen": "salle1",
    "epreuve": "MI"
  },
  {
    "id": "G135017366",
    "nom": "Harib",
    "prenom": "Sara",
    "numero_examen": 1351,
    "salle_examen": "salle2",
    "epreuve": "MI"
  },
  {
    "id": "F133152550",
    "nom": "Hassan",
    "prenom": "Assmaa",
    "numero_examen": 1352,
    "salle_examen": "salle2",
    "epreuve": "MI"
  },
  {
    "id": "R134513688",
    "nom": "Hassouna",
    "prenom": "Ismail",
    "numero_examen": 1353,
    "salle_examen": "salle2",
    "epreuve": "MI"
  },
  {
    "id": "F134057256",
    "nom": "Hassouna",
    "prenom": "Raihana",
    "numero_examen": 1354,
    "salle_examen": "salle2",
    "epreuve": "MI"
  },
  {
    "id": "F141067212",
    "nom": "Haytom",
    "prenom": "Aymen",
    "numero_examen": 1355,
    "salle_examen": "salle2",
    "epreuve": "MI"
  },
  {
    "id": "H130010895",
    "nom": "Hida",
    "prenom": "Mouad",
    "numero_examen": 1356,
    "salle_examen": "salle2",
    "epreuve": "MI"
  },
  {
    "id": "R130192310",
    "nom": "Homman",
    "prenom": "Samira",
    "numero_examen": 1357,
    "salle_examen": "salle2",
    "epreuve": "MI"
  },
  {
    "id": "H130119724",
    "nom": "Houbban",
    "prenom": "Mohammed",
    "numero_examen": 1358,
    "salle_examen": "salle2",
    "epreuve": "MI"
  },
  {
    "id": "P130180944",
    "nom": "Ibnelma",
    "prenom": "Ihsane",
    "numero_examen": 1359,
    "salle_examen": "salle2",
    "epreuve": "MI"
  },
  {
    "id": "Z230700135",
    "nom": "Ibrahimi",
    "prenom": "Anas",
    "numero_examen": 1360,
    "salle_examen": "salle2",
    "epreuve": "MI"
  },
  {
    "id": "R137916656",
    "nom": "Ibrahimi",
    "prenom": "Khaoula",
    "numero_examen": 1361,
    "salle_examen": "salle2",
    "epreuve": "MI"
  },
  {
    "id": "E149095037",
    "nom": "Idnasser",
    "prenom": "Yassine",
    "numero_examen": 1362,
    "salle_examen": "salle2",
    "epreuve": "MI"
  },
  {
    "id": "N120042319",
    "nom": "Idrissi Meliani",
    "prenom": "Hamza",
    "numero_examen": 1363,
    "salle_examen": "salle2",
    "epreuve": "MI"
  },
  {
    "id": "R138338659",
    "nom": "Imchtka",
    "prenom": "Abdelhak",
    "numero_examen": 1364,
    "salle_examen": "salle2",
    "epreuve": "MI"
  },
  {
    "id": "D130041180",
    "nom": "Imgharn",
    "prenom": "Noureddine",
    "numero_examen": 1365,
    "salle_examen": "salle2",
    "epreuve": "MI"
  },
  {
    "id": "L147105765",
    "nom": "Imouzaz",
    "prenom": "Nabila",
    "numero_examen": 1366,
    "salle_examen": "salle2",
    "epreuve": "MI"
  },
  {
    "id": "G132483079",
    "nom": "Inhid",
    "prenom": "Hanane",
    "numero_examen": 1367,
    "salle_examen": "salle2",
    "epreuve": "MI"
  },
  {
    "id": "D137214452",
    "nom": "Islaouine",
    "prenom": "Mouad",
    "numero_examen": 1368,
    "salle_examen": "salle2",
    "epreuve": "MI"
  },
  {
    "id": "H130005383",
    "nom": "Jabri",
    "prenom": "Mohammed Ali",
    "numero_examen": 1369,
    "salle_examen": "salle2",
    "epreuve": "MI"
  },
  {
    "id": "R135787884",
    "nom": "Jaffal",
    "prenom": "Mohammed",
    "numero_examen": 1370,
    "salle_examen": "salle2",
    "epreuve": "MI"
  },
  {
    "id": "S132248224",
    "nom": "Jaghdor",
    "prenom": "Ilyass",
    "numero_examen": 1371,
    "salle_examen": "salle2",
    "epreuve": "MI"
  },
  {
    "id": "D137081917",
    "nom": "Jalaou",
    "prenom": "Mohamed",
    "numero_examen": 1372,
    "salle_examen": "salle2",
    "epreuve": "MI"
  },
  {
    "id": "UD19151",
    "nom": "Jamlaoui",
    "prenom": "Ikhlass",
    "numero_examen": 1373,
    "salle_examen": "salle2",
    "epreuve": "MI"
  },
  {
    "id": "R130071216",
    "nom": "Janati",
    "prenom": "Ayman",
    "numero_examen": 1374,
    "salle_examen": "salle2",
    "epreuve": "MI"
  },
  {
    "id": "R130174850",
    "nom": "Jarbouai",
    "prenom": "Doha",
    "numero_examen": 1375,
    "salle_examen": "salle2",
    "epreuve": "MI"
  },
  {
    "id": "R137303663",
    "nom": "Jarmouni",
    "prenom": "Anas",
    "numero_examen": 1376,
    "salle_examen": "salle2",
    "epreuve": "MI"
  },
  {
    "id": "R132491266",
    "nom": "Jazoul",
    "prenom": "Mohamed Amine",
    "numero_examen": 1377,
    "salle_examen": "salle2",
    "epreuve": "MI"
  },
  {
    "id": "H130410248",
    "nom": "Jboub",
    "prenom": "Wissal",
    "numero_examen": 1378,
    "salle_examen": "salle2",
    "epreuve": "MI"
  },
  {
    "id": "D145027957",
    "nom": "Jebbour",
    "prenom": "Saad",
    "numero_examen": 1379,
    "salle_examen": "salle2",
    "epreuve": "MI"
  },
  {
    "id": "D135674733",
    "nom": "Jimi",
    "prenom": "Azeddine",
    "numero_examen": 1380,
    "salle_examen": "salle2",
    "epreuve": "MI"
  },
  {
    "id": "0837654045",
    "nom": "Kadade Mahamadou",
    "prenom": "Bassirou",
    "numero_examen": 1381,
    "salle_examen": "salle2",
    "epreuve": "MI"
  },
  {
    "id": "H138074915",
    "nom": "Kaddani",
    "prenom": "Layla",
    "numero_examen": 1382,
    "salle_examen": "salle2",
    "epreuve": "MI"
  },
  {
    "id": "2300050041",
    "nom": "Kadio",
    "prenom": "Abdoul Wahab",
    "numero_examen": 1383,
    "salle_examen": "salle2",
    "epreuve": "MI"
  },
  {
    "id": "R130097227",
    "nom": "Kamal",
    "prenom": "Salma",
    "numero_examen": 1384,
    "salle_examen": "salle2",
    "epreuve": "MI"
  },
  {
    "id": "ESTO201104",
    "nom": "Karambiri",
    "prenom": "Issa Aziz",
    "numero_examen": 1385,
    "salle_examen": "salle2",
    "epreuve": "MI"
  },
  {
    "id": "X231060172",
    "nom": "Keita",
    "prenom": "Palingwende Izdine Djamilatou",
    "numero_examen": 1386,
    "salle_examen": "salle2",
    "epreuve": "MI"
  },
  {
    "id": "X231070007",
    "nom": "Kere",
    "prenom": "Abdoul-Wahab",
    "numero_examen": 1387,
    "salle_examen": "salle2",
    "epreuve": "MI"
  },
  {
    "id": "M130037796",
    "nom": "Kerissene",
    "prenom": "Ibtissam",
    "numero_examen": 1388,
    "salle_examen": "salle2",
    "epreuve": "MI"
  },
  {
    "id": "P139173226",
    "nom": "Khadiri",
    "prenom": "Imane",
    "numero_examen": 1389,
    "salle_examen": "salle2",
    "epreuve": "MI"
  },
  {
    "id": "G136708433",
    "nom": "Khatim",
    "prenom": "Salma",
    "numero_examen": 1390,
    "salle_examen": "salle2",
    "epreuve": "MI"
  },
  {
    "id": "P135484767",
    "nom": "Khayat",
    "prenom": "Israe",
    "numero_examen": 1391,
    "salle_examen": "salle2",
    "epreuve": "MI"
  },
  {
    "id": "R130016646",
    "nom": "Khindouf",
    "prenom": "Salma",
    "numero_examen": 1392,
    "salle_examen": "salle2",
    "epreuve": "MI"
  },
  {
    "id": "D130021086",
    "nom": "Khouden",
    "prenom": "Abdellah",
    "numero_examen": 1393,
    "salle_examen": "salle2",
    "epreuve": "MI"
  },
  {
    "id": "2300050040",
    "nom": "Kientega",
    "prenom": "Wendlasida Rodrigue",
    "numero_examen": 1394,
    "salle_examen": "salle2",
    "epreuve": "MI"
  },
  {
    "id": "P132446607",
    "nom": "Klilich",
    "prenom": "Sara",
    "numero_examen": 1395,
    "salle_examen": "salle2",
    "epreuve": "MI"
  },
  {
    "id": "R133683282",
    "nom": "Kniri",
    "prenom": "Doha",
    "numero_examen": 1396,
    "salle_examen": "salle2",
    "epreuve": "MI"
  },
  {
    "id": "ESTO260305",
    "nom": "Konate",
    "prenom": "Abdoul Karim",
    "numero_examen": 1397,
    "salle_examen": "salle2",
    "epreuve": "MI"
  },
  {
    "id": "2392210012",
    "nom": "Konkobo",
    "prenom": "Windpouyire  Faissal Cedric",
    "numero_examen": 1398,
    "salle_examen": "salle2",
    "epreuve": "MI"
  },
  {
    "id": "N143055462",
    "nom": "Kouah",
    "prenom": "Abdelkader",
    "numero_examen": 1399,
    "salle_examen": "salle2",
    "epreuve": "MI"
  },
  {
    "id": "C137100457",
    "nom": "Koubi",
    "prenom": "Mohamed-Yassine",
    "numero_examen": 1400,
    "salle_examen": "salle2",
    "epreuve": "MI"
  },
  {
    "id": "R120067536",
    "nom": "Kraim",
    "prenom": "Ayoub",
    "numero_examen": 1401,
    "salle_examen": "salle3",
    "epreuve": "MI"
  },
  {
    "id": "D130016440",
    "nom": "Kremcht",
    "prenom": "Ilyass",
    "numero_examen": 1402,
    "salle_examen": "salle3",
    "epreuve": "MI"
  },
  {
    "id": "L134181235",
    "nom": "Laamari",
    "prenom": "Kawtar",
    "numero_examen": 1403,
    "salle_examen": "salle3",
    "epreuve": "MI"
  },
  {
    "id": "G130325125",
    "nom": "Laaouafi",
    "prenom": "Fatiha",
    "numero_examen": 1404,
    "salle_examen": "salle3",
    "epreuve": "MI"
  },
  {
    "id": "D133655681",
    "nom": "Laaouina",
    "prenom": "Wisal",
    "numero_examen": 1405,
    "salle_examen": "salle3",
    "epreuve": "MI"
  },
  {
    "id": "D139364324",
    "nom": "Laaraj",
    "prenom": "Mohamed",
    "numero_examen": 1406,
    "salle_examen": "salle3",
    "epreuve": "MI"
  },
  {
    "id": "M132136968",
    "nom": "Laaribi",
    "prenom": "Mohamed",
    "numero_examen": 1407,
    "salle_examen": "salle3",
    "epreuve": "MI"
  },
  {
    "id": "G138006973",
    "nom": "Lachhab",
    "prenom": "Ismail",
    "numero_examen": 1408,
    "salle_examen": "salle3",
    "epreuve": "MI"
  },
  {
    "id": "S137061730",
    "nom": "Lafkiar",
    "prenom": "Rachid",
    "numero_examen": 1409,
    "salle_examen": "salle3",
    "epreuve": "MI"
  },
  {
    "id": "A135025120",
    "nom": "Laghmir",
    "prenom": "Jihane",
    "numero_examen": 1410,
    "salle_examen": "salle3",
    "epreuve": "MI"
  },
  {
    "id": "G133023105",
    "nom": "Lahder",
    "prenom": "Abdelaziz",
    "numero_examen": 1411,
    "salle_examen": "salle3",
    "epreuve": "MI"
  },
  {
    "id": "R130485910",
    "nom": "Lahrach",
    "prenom": "Nour",
    "numero_examen": 1412,
    "salle_examen": "salle3",
    "epreuve": "MI"
  },
  {
    "id": "D137247089",
    "nom": "Lakfife",
    "prenom": "Elhoussaine",
    "numero_examen": 1413,
    "salle_examen": "salle3",
    "epreuve": "MI"
  },
  {
    "id": "S133161063",
    "nom": "Lakhlit",
    "prenom": "Boutaina",
    "numero_examen": 1414,
    "salle_examen": "salle3",
    "epreuve": "MI"
  },
  {
    "id": "G139178189",
    "nom": "Lakiz",
    "prenom": "Oussama",
    "numero_examen": 1415,
    "salle_examen": "salle3",
    "epreuve": "MI"
  },
  {
    "id": "R120032479",
    "nom": "Lakroud",
    "prenom": "Doha",
    "numero_examen": 1416,
    "salle_examen": "salle3",
    "epreuve": "MI"
  },
  {
    "id": "J131106736",
    "nom": "Laksiouer",
    "prenom": "Nour El Houda",
    "numero_examen": 1417,
    "salle_examen": "salle3",
    "epreuve": "MI"
  },
  {
    "id": "F132216382",
    "nom": "Lamachi",
    "prenom": "Khalid",
    "numero_examen": 1418,
    "salle_examen": "salle3",
    "epreuve": "MI"
  },
  {
    "id": "E136187504",
    "nom": "Lamalem",
    "prenom": "Bassma",
    "numero_examen": 1419,
    "salle_examen": "salle3",
    "epreuve": "MI"
  },
  {
    "id": "H137036209",
    "nom": "Lamkadmi",
    "prenom": "Loubna",
    "numero_examen": 1420,
    "salle_examen": "salle3",
    "epreuve": "MI"
  },
  {
    "id": "R120063835",
    "nom": "Lamnabhi",
    "prenom": "Ilham",
    "numero_examen": 1421,
    "salle_examen": "salle3",
    "epreuve": "MI"
  },
  {
    "id": "N134380979",
    "nom": "Lamrini",
    "prenom": "Ishak",
    "numero_examen": 1422,
    "salle_examen": "salle3",
    "epreuve": "MI"
  },
  {
    "id": "G139191964",
    "nom": "Lasfar",
    "prenom": "Fatima Zahra",
    "numero_examen": 1423,
    "salle_examen": "salle3",
    "epreuve": "MI"
  },
  {
    "id": "R130438900",
    "nom": "Latrache",
    "prenom": "Hajar",
    "numero_examen": 1424,
    "salle_examen": "salle3",
    "epreuve": "MI"
  },
  {
    "id": "R134769337",
    "nom": "Lechheb",
    "prenom": "Wail",
    "numero_examen": 1425,
    "salle_examen": "salle3",
    "epreuve": "MI"
  },
  {
    "id": "G134619631",
    "nom": "Loukid",
    "prenom": "Asmaa",
    "numero_examen": 1426,
    "salle_examen": "salle3",
    "epreuve": "MI"
  },
  {
    "id": "F136090425",
    "nom": "Mabrouk",
    "prenom": "Kawtar",
    "numero_examen": 1427,
    "salle_examen": "salle3",
    "epreuve": "MI"
  },
  {
    "id": "J135237546",
    "nom": "Machach",
    "prenom": "Marwa",
    "numero_examen": 1428,
    "salle_examen": "salle3",
    "epreuve": "MI"
  },
  {
    "id": "C135128526",
    "nom": "Machtaq",
    "prenom": "Zahira",
    "numero_examen": 1429,
    "salle_examen": "salle3",
    "epreuve": "MI"
  },
  {
    "id": "2023000002",
    "nom": "Mahamadou Elh Issoufou",
    "prenom": "Maimounatou",
    "numero_examen": 1430,
    "salle_examen": "salle3",
    "epreuve": "MI"
  },
  {
    "id": "R131438608",
    "nom": "Mahboub",
    "prenom": "Marouane",
    "numero_examen": 1431,
    "salle_examen": "salle3",
    "epreuve": "MI"
  },
  {
    "id": "R134929304",
    "nom": "Maizi",
    "prenom": "Lina",
    "numero_examen": 1432,
    "salle_examen": "salle3",
    "epreuve": "MI"
  },
  {
    "id": "R138451491",
    "nom": "Majoch",
    "prenom": "Yassmine",
    "numero_examen": 1433,
    "salle_examen": "salle3",
    "epreuve": "MI"
  },
  {
    "id": "F135031004",
    "nom": "Makboul",
    "prenom": "Ilhame",
    "numero_examen": 1434,
    "salle_examen": "salle3",
    "epreuve": "MI"
  },
  {
    "id": "F130164509",
    "nom": "Makdad",
    "prenom": "Mohamed Amine",
    "numero_examen": 1435,
    "salle_examen": "salle3",
    "epreuve": "MI"
  },
  {
    "id": "R130105385",
    "nom": "Makkawy",
    "prenom": "Zouhair",
    "numero_examen": 1436,
    "salle_examen": "salle3",
    "epreuve": "MI"
  },
  {
    "id": "H135309176",
    "nom": "Makrani",
    "prenom": "Safae",
    "numero_examen": 1437,
    "salle_examen": "salle3",
    "epreuve": "MI"
  },
  {
    "id": "G137109063",
    "nom": "Malal",
    "prenom": "Yassine",
    "numero_examen": 1438,
    "salle_examen": "salle3",
    "epreuve": "MI"
  },
  {
    "id": "D137572688",
    "nom": "Manar El Idrissi",
    "prenom": "Hamza",
    "numero_examen": 1439,
    "salle_examen": "salle3",
    "epreuve": "MI"
  },
  {
    "id": "R131358556",
    "nom": "Marhaoui",
    "prenom": "Ikram",
    "numero_examen": 1440,
    "salle_examen": "salle3",
    "epreuve": "MI"
  },
  {
    "id": "M130126808",
    "nom": "Marhouni",
    "prenom": "Rachida",
    "numero_examen": 1441,
    "salle_examen": "salle3",
    "epreuve": "MI"
  },
  {
    "id": "R137215906",
    "nom": "Marzaq",
    "prenom": "Asmae",
    "numero_examen": 1442,
    "salle_examen": "salle3",
    "epreuve": "MI"
  },
  {
    "id": "D137756725",
    "nom": "Marzougui",
    "prenom": "Adnane",
    "numero_examen": 1443,
    "salle_examen": "salle3",
    "epreuve": "MI"
  },
  {
    "id": "2023000003",
    "nom": "Massalabi Oumarou",
    "prenom": "Almajir",
    "numero_examen": 1444,
    "salle_examen": "salle3",
    "epreuve": "MI"
  },
  {
    "id": "P134480579",
    "nom": "Mechale",
    "prenom": "Islam",
    "numero_examen": 1445,
    "salle_examen": "salle3",
    "epreuve": "MI"
  },
  {
    "id": "R136378204",
    "nom": "Medinou",
    "prenom": "Soukaina",
    "numero_examen": 1446,
    "salle_examen": "salle3",
    "epreuve": "MI"
  },
  {
    "id": "N131287193",
    "nom": "Mejjani",
    "prenom": "Chaimae",
    "numero_examen": 1447,
    "salle_examen": "salle3",
    "epreuve": "MI"
  },
  {
    "id": "L133159393",
    "nom": "Mekkaoui",
    "prenom": "Imane",
    "numero_examen": 1448,
    "salle_examen": "salle3",
    "epreuve": "MI"
  },
  {
    "id": "R130378292",
    "nom": "Mellah",
    "prenom": "Marwa",
    "numero_examen": 1449,
    "salle_examen": "salle3",
    "epreuve": "MI"
  },
  {
    "id": "M131441391",
    "nom": "Menai",
    "prenom": "Douae",
    "numero_examen": 1450,
    "salle_examen": "salle3",
    "epreuve": "MI"
  },
  {
    "id": "G134586446",
    "nom": "Messaoudi",
    "prenom": "Fadwa",
    "numero_examen": 1451,
    "salle_examen": "salle4",
    "epreuve": "MI"
  },
  {
    "id": "M133375168",
    "nom": "Messaoudi",
    "prenom": "Manar",
    "numero_examen": 1452,
    "salle_examen": "salle4",
    "epreuve": "MI"
  },
  {
    "id": "R130608198",
    "nom": "Mifdal",
    "prenom": "Ilyas",
    "numero_examen": 1453,
    "salle_examen": "salle4",
    "epreuve": "MI"
  },
  {
    "id": "B137030662",
    "nom": "Misbah",
    "prenom": "Kaoutar",
    "numero_examen": 1454,
    "salle_examen": "salle4",
    "epreuve": "MI"
  },
  {
    "id": "R130170329",
    "nom": "Moho Amer",
    "prenom": "Akram",
    "numero_examen": 1455,
    "salle_examen": "salle4",
    "epreuve": "MI"
  },
  {
    "id": "R110173988",
    "nom": "Mondir",
    "prenom": "Salma",
    "numero_examen": 1456,
    "salle_examen": "salle4",
    "epreuve": "MI"
  },
  {
    "id": "G137616235",
    "nom": "Monybe",
    "prenom": "Lina",
    "numero_examen": 1457,
    "salle_examen": "salle4",
    "epreuve": "MI"
  },
  {
    "id": "R120076281",
    "nom": "Morafik",
    "prenom": "Ibtissam",
    "numero_examen": 1458,
    "salle_examen": "salle4",
    "epreuve": "MI"
  },
  {
    "id": "M130038597",
    "nom": "Mossaid",
    "prenom": "Abdelmoughit",
    "numero_examen": 1459,
    "salle_examen": "salle4",
    "epreuve": "MI"
  },
  {
    "id": "R139331396",
    "nom": "Mouadi",
    "prenom": "Yassine",
    "numero_examen": 1460,
    "salle_examen": "salle4",
    "epreuve": "MI"
  },
  {
    "id": "K131260033",
    "nom": "Mouhaddab",
    "prenom": "Oumaima",
    "numero_examen": 1461,
    "salle_examen": "salle4",
    "epreuve": "MI"
  },
  {
    "id": "D136454509",
    "nom": "Mouid",
    "prenom": "Abdelaali",
    "numero_examen": 1462,
    "salle_examen": "salle4",
    "epreuve": "MI"
  },
  {
    "id": "R132688397",
    "nom": "Moujahid",
    "prenom": "Salaheddine",
    "numero_examen": 1463,
    "salle_examen": "salle4",
    "epreuve": "MI"
  },
  {
    "id": "R131568971",
    "nom": "Moukhtari",
    "prenom": "Nouhaila",
    "numero_examen": 1464,
    "salle_examen": "salle4",
    "epreuve": "MI"
  },
  {
    "id": "R136569329",
    "nom": "Moukhtari",
    "prenom": "Salma",
    "numero_examen": 1465,
    "salle_examen": "salle4",
    "epreuve": "MI"
  },
  {
    "id": "L136177566",
    "nom": "Moukrim",
    "prenom": "Aya",
    "numero_examen": 1466,
    "salle_examen": "salle4",
    "epreuve": "MI"
  },
  {
    "id": "Y135012254",
    "nom": "Moumni",
    "prenom": "Walid",
    "numero_examen": 1467,
    "salle_examen": "salle4",
    "epreuve": "MI"
  },
  {
    "id": "D140072803",
    "nom": "Mounji",
    "prenom": "Hajar",
    "numero_examen": 1468,
    "salle_examen": "salle4",
    "epreuve": "MI"
  },
  {
    "id": "R132256835",
    "nom": "Mourhiya",
    "prenom": "Imane",
    "numero_examen": 1469,
    "salle_examen": "salle4",
    "epreuve": "MI"
  },
  {
    "id": "2392210036",
    "nom": "Moussa Boubacar",
    "prenom": "Abdoul Majid",
    "numero_examen": 1470,
    "salle_examen": "salle4",
    "epreuve": "MI"
  },
  {
    "id": "2392210052",
    "nom": "Moussa Mahaman",
    "prenom": "Ahmed",
    "numero_examen": 1471,
    "salle_examen": "salle4",
    "epreuve": "MI"
  },
  {
    "id": "R141029873",
    "nom": "Moussaoui",
    "prenom": "Abderrahim",
    "numero_examen": 1472,
    "salle_examen": "salle4",
    "epreuve": "MI"
  },
  {
    "id": "R135769937",
    "nom": "Moutaouie",
    "prenom": "Anas",
    "numero_examen": 1473,
    "salle_examen": "salle4",
    "epreuve": "MI"
  },
  {
    "id": "N120002308",
    "nom": "Mrabti",
    "prenom": "Yassir",
    "numero_examen": 1474,
    "salle_examen": "salle4",
    "epreuve": "MI"
  },
  {
    "id": "D135326570",
    "nom": "M'Rak",
    "prenom": "Abdellah",
    "numero_examen": 1475,
    "salle_examen": "salle4",
    "epreuve": "MI"
  },
  {
    "id": "R110161831",
    "nom": "Msillane",
    "prenom": "Adnane",
    "numero_examen": 1476,
    "salle_examen": "salle4",
    "epreuve": "MI"
  },
  {
    "id": "N134336450",
    "nom": "Nabil",
    "prenom": "Chaima",
    "numero_examen": 1477,
    "salle_examen": "salle4",
    "epreuve": "MI"
  },
  {
    "id": "L140019434",
    "nom": "Naciri",
    "prenom": "Abdelhaq",
    "numero_examen": 1478,
    "salle_examen": "salle4",
    "epreuve": "MI"
  },
  {
    "id": "J110073360",
    "nom": "Naciri",
    "prenom": "Sarah",
    "numero_examen": 1479,
    "salle_examen": "salle4",
    "epreuve": "MI"
  },
  {
    "id": "R139316585",
    "nom": "Nahil",
    "prenom": "Wissal",
    "numero_examen": 1480,
    "salle_examen": "salle4",
    "epreuve": "MI"
  },
  {
    "id": "G139555271",
    "nom": "Nait Ouahmane",
    "prenom": "Abdellah",
    "numero_examen": 1481,
    "salle_examen": "salle4",
    "epreuve": "MI"
  },
  {
    "id": "Z222601347",
    "nom": "Najdi",
    "prenom": "Med Nourredine",
    "numero_examen": 1482,
    "salle_examen": "salle4",
    "epreuve": "MI"
  },
  {
    "id": "K136493706",
    "nom": "Naji",
    "prenom": "Youssef",
    "numero_examen": 1483,
    "salle_examen": "salle4",
    "epreuve": "MI"
  },
  {
    "id": "M134306522",
    "nom": "Najjari",
    "prenom": "Anass",
    "numero_examen": 1484,
    "salle_examen": "salle4",
    "epreuve": "MI"
  },
  {
    "id": "L139327631",
    "nom": "Namaoui",
    "prenom": "Fatimazahra",
    "numero_examen": 1485,
    "salle_examen": "salle4",
    "epreuve": "MI"
  },
  {
    "id": "R130223778",
    "nom": "Namir",
    "prenom": "Yahya",
    "numero_examen": 1486,
    "salle_examen": "salle4",
    "epreuve": "MI"
  },
  {
    "id": "F135102418",
    "nom": "Naouali",
    "prenom": "Houssam",
    "numero_examen": 1487,
    "salle_examen": "salle4",
    "epreuve": "MI"
  },
  {
    "id": "R134479179",
    "nom": "Naraki",
    "prenom": "Aya",
    "numero_examen": 1488,
    "salle_examen": "salle4",
    "epreuve": "MI"
  },
  {
    "id": "R100045631",
    "nom": "Narjiss",
    "prenom": "Abdelkarim",
    "numero_examen": 1489,
    "salle_examen": "salle4",
    "epreuve": "MI"
  },
  {
    "id": "N137366185",
    "nom": "Nfissi",
    "prenom": "Mohamed Amine",
    "numero_examen": 1490,
    "salle_examen": "salle4",
    "epreuve": "MI"
  },
  {
    "id": "R100124859",
    "nom": "Nil",
    "prenom": "Aya",
    "numero_examen": 1491,
    "salle_examen": "salle4",
    "epreuve": "MI"
  },
  {
    "id": "R130483696",
    "nom": "Niri",
    "prenom": "Ayoub",
    "numero_examen": 1492,
    "salle_examen": "salle4",
    "epreuve": "MI"
  },
  {
    "id": "K135238821",
    "nom": "Nouini",
    "prenom": "Fatima -Ezzahra",
    "numero_examen": 1493,
    "salle_examen": "salle4",
    "epreuve": "MI"
  },
  {
    "id": "K130065415",
    "nom": "Otmani",
    "prenom": "Mohsine",
    "numero_examen": 1494,
    "salle_examen": "salle4",
    "epreuve": "MI"
  },
  {
    "id": "R149020902",
    "nom": "Ouabi",
    "prenom": "Hiba",
    "numero_examen": 1495,
    "salle_examen": "salle4",
    "epreuve": "MI"
  },
  {
    "id": "R130133060",
    "nom": "Ouahlim",
    "prenom": "Fatima",
    "numero_examen": 1496,
    "salle_examen": "salle4",
    "epreuve": "MI"
  },
  {
    "id": "M130112494",
    "nom": "Ouaomar",
    "prenom": "Marouane",
    "numero_examen": 1497,
    "salle_examen": "salle4",
    "epreuve": "MI"
  },
  {
    "id": "R138761647",
    "nom": "Ouatile",
    "prenom": "Yousra",
    "numero_examen": 1498,
    "salle_examen": "salle4",
    "epreuve": "MI"
  },
  {
    "id": "G136608602",
    "nom": "Oubaih",
    "prenom": "Zakaria",
    "numero_examen": 1499,
    "salle_examen": "salle4",
    "epreuve": "MI"
  },
  {
    "id": "D145040361",
    "nom": "Oubairouk",
    "prenom": "Chaima",
    "numero_examen": 1500,
    "salle_examen": "salle4",
    "epreuve": "MI"
  },
  {
    "id": "M130114707",
    "nom": "Oubouisk",
    "prenom": "Amine",
    "numero_examen": 1501,
    "salle_examen": "salle4",
    "epreuve": "MI"
  },
  {
    "id": "M131173904",
    "nom": "Ou-Briche",
    "prenom": "Mohamed",
    "numero_examen": 1502,
    "salle_examen": "salle5",
    "epreuve": "MI"
  },
  {
    "id": "M139285190",
    "nom": "Oubza",
    "prenom": "Fadoua",
    "numero_examen": 1503,
    "salle_examen": "salle5",
    "epreuve": "MI"
  },
  {
    "id": "G133797758",
    "nom": "Ouchta",
    "prenom": "Ayoub",
    "numero_examen": 1504,
    "salle_examen": "salle5",
    "epreuve": "MI"
  },
  {
    "id": "M139413794",
    "nom": "Oudadda",
    "prenom": "Salah Eddine",
    "numero_examen": 1505,
    "salle_examen": "salle5",
    "epreuve": "MI"
  },
  {
    "id": "R120023062",
    "nom": "Ouerdani",
    "prenom": "Aya",
    "numero_examen": 1506,
    "salle_examen": "salle5",
    "epreuve": "MI"
  },
  {
    "id": "G136700007",
    "nom": "Oufnine",
    "prenom": "Fatima Ezzahra",
    "numero_examen": 1507,
    "salle_examen": "salle5",
    "epreuve": "MI"
  },
  {
    "id": "N135121403",
    "nom": "Ouhssain",
    "prenom": "Hamza",
    "numero_examen": 1508,
    "salle_examen": "salle5",
    "epreuve": "MI"
  },
  {
    "id": "L131225373",
    "nom": "Oukessou",
    "prenom": "Chorouk",
    "numero_examen": 1509,
    "salle_examen": "salle5",
    "epreuve": "MI"
  },
  {
    "id": "E100102508",
    "nom": "Ouladkrit",
    "prenom": "Anas",
    "numero_examen": 1510,
    "salle_examen": "salle5",
    "epreuve": "MI"
  },
  {
    "id": "F130025460",
    "nom": "Oulhanafi",
    "prenom": "Houria",
    "numero_examen": 1511,
    "salle_examen": "salle5",
    "epreuve": "MI"
  },
  {
    "id": "D139278089",
    "nom": "Oumessaoud",
    "prenom": "Hajar",
    "numero_examen": 1512,
    "salle_examen": "salle5",
    "epreuve": "MI"
  },
  {
    "id": "M130428406",
    "nom": "Outalha",
    "prenom": "Haddou",
    "numero_examen": 1513,
    "salle_examen": "salle5",
    "epreuve": "MI"
  },
  {
    "id": "L136119409",
    "nom": "Qatib",
    "prenom": "Kanza",
    "numero_examen": 1514,
    "salle_examen": "salle5",
    "epreuve": "MI"
  },
  {
    "id": "D149022164",
    "nom": "Rabouane",
    "prenom": "Nour-Eddine",
    "numero_examen": 1515,
    "salle_examen": "salle5",
    "epreuve": "MI"
  },
  {
    "id": "R134315766",
    "nom": "Rafik",
    "prenom": "Oussama",
    "numero_examen": 1516,
    "salle_examen": "salle5",
    "epreuve": "MI"
  },
  {
    "id": "ESTO010605",
    "nom": "Rajaotiana",
    "prenom": "Rinoh Dominique",
    "numero_examen": 1517,
    "salle_examen": "salle5",
    "epreuve": "MI"
  },
  {
    "id": "J138387920",
    "nom": "Razzouk",
    "prenom": "Majda",
    "numero_examen": 1518,
    "salle_examen": "salle5",
    "epreuve": "MI"
  },
  {
    "id": "H135267121",
    "nom": "Resoun",
    "prenom": "Achraf",
    "numero_examen": 1519,
    "salle_examen": "salle5",
    "epreuve": "MI"
  },
  {
    "id": "S131175369",
    "nom": "Rhafri",
    "prenom": "Fatima Zahra",
    "numero_examen": 1520,
    "salle_examen": "salle5",
    "epreuve": "MI"
  },
  {
    "id": "E139222835",
    "nom": "Rharib",
    "prenom": "Chahd",
    "numero_examen": 1521,
    "salle_examen": "salle5",
    "epreuve": "MI"
  },
  {
    "id": "R137292418",
    "nom": "Rhazoui",
    "prenom": "Omar",
    "numero_examen": 1522,
    "salle_examen": "salle5",
    "epreuve": "MI"
  },
  {
    "id": "P139269331",
    "nom": "Rhoni Aref",
    "prenom": "Manal",
    "numero_examen": 1523,
    "salle_examen": "salle5",
    "epreuve": "MI"
  },
  {
    "id": "R140036407",
    "nom": "Rida Chafi",
    "prenom": "Anass",
    "numero_examen": 1524,
    "salle_examen": "salle5",
    "epreuve": "MI"
  },
  {
    "id": "J110065131",
    "nom": "Rochdi",
    "prenom": "Rihab",
    "numero_examen": 1525,
    "salle_examen": "salle5",
    "epreuve": "MI"
  },
  {
    "id": "R133398499",
    "nom": "Roukissy",
    "prenom": "Said",
    "numero_examen": 1526,
    "salle_examen": "salle5",
    "epreuve": "MI"
  },
  {
    "id": "D120021302",
    "nom": "Rzouk",
    "prenom": "Said",
    "numero_examen": 1527,
    "salle_examen": "salle5",
    "epreuve": "MI"
  },
  {
    "id": "D130418857",
    "nom": "Saaidi",
    "prenom": "Safa",
    "numero_examen": 1528,
    "salle_examen": "salle5",
    "epreuve": "MI"
  },
  {
    "id": "R136337289",
    "nom": "Sabik",
    "prenom": "Rihame",
    "numero_examen": 1529,
    "salle_examen": "salle5",
    "epreuve": "MI"
  },
  {
    "id": "C134129397",
    "nom": "Sabir",
    "prenom": "Hana",
    "numero_examen": 1530,
    "salle_examen": "salle5",
    "epreuve": "MI"
  },
  {
    "id": "R130198500",
    "nom": "Sabir",
    "prenom": "Ikram",
    "numero_examen": 1531,
    "salle_examen": "salle5",
    "epreuve": "MI"
  },
  {
    "id": "M131502504",
    "nom": "Sabri",
    "prenom": "Ahmed Amine",
    "numero_examen": 1532,
    "salle_examen": "salle5",
    "epreuve": "MI"
  },
  {
    "id": "R144085975",
    "nom": "Sabri",
    "prenom": "Youssef",
    "numero_examen": 1533,
    "salle_examen": "salle5",
    "epreuve": "MI"
  },
  {
    "id": "D131046092",
    "nom": "Sabri",
    "prenom": "Zakariya",
    "numero_examen": 1534,
    "salle_examen": "salle5",
    "epreuve": "MI"
  },
  {
    "id": "R140049756",
    "nom": "Sadik",
    "prenom": "Hamza",
    "numero_examen": 1535,
    "salle_examen": "salle5",
    "epreuve": "MI"
  },
  {
    "id": "M138376692",
    "nom": "Saffou",
    "prenom": "Soufiane",
    "numero_examen": 1536,
    "salle_examen": "salle5",
    "epreuve": "MI"
  },
  {
    "id": "K139184090",
    "nom": "Saffoury",
    "prenom": "Zineb",
    "numero_examen": 1537,
    "salle_examen": "salle5",
    "epreuve": "MI"
  },
  {
    "id": "G136694272",
    "nom": "Safrioui",
    "prenom": "Azeddine",
    "numero_examen": 1538,
    "salle_examen": "salle5",
    "epreuve": "MI"
  },
  {
    "id": "ESTO201206",
    "nom": "Said Ahmed",
    "prenom": "Roukia",
    "numero_examen": 1539,
    "salle_examen": "salle5",
    "epreuve": "MI"
  },
  {
    "id": "R132510103",
    "nom": "Saila",
    "prenom": "Hafsa",
    "numero_examen": 1540,
    "salle_examen": "salle5",
    "epreuve": "MI"
  },
  {
    "id": "N149065915",
    "nom": "Salhi",
    "prenom": "Fatima Zohra",
    "numero_examen": 1541,
    "salle_examen": "salle5",
    "epreuve": "MI"
  },
  {
    "id": "H145065530",
    "nom": "Salhi",
    "prenom": "Imane",
    "numero_examen": 1542,
    "salle_examen": "salle5",
    "epreuve": "MI"
  },
  {
    "id": "R137809399",
    "nom": "Salim El Qalb",
    "prenom": "Yahya",
    "numero_examen": 1543,
    "salle_examen": "salle5",
    "epreuve": "MI"
  },
  {
    "id": "K134249050",
    "nom": "Sallam",
    "prenom": "Hajar",
    "numero_examen": 1544,
    "salle_examen": "salle5",
    "epreuve": "MI"
  },
  {
    "id": "R135488172",
    "nom": "Salmi",
    "prenom": "Rabii",
    "numero_examen": 1545,
    "salle_examen": "salle5",
    "epreuve": "MI"
  },
  {
    "id": "2320231101",
    "nom": "Sangare",
    "prenom": "Boris Eleazar",
    "numero_examen": 1546,
    "salle_examen": "salle5",
    "epreuve": "MI"
  },
  {
    "id": "R135798964",
    "nom": "Sayadi",
    "prenom": "Mohammed Amine",
    "numero_examen": 1547,
    "salle_examen": "salle5",
    "epreuve": "MI"
  },
  {
    "id": "N134361502",
    "nom": "Sbia",
    "prenom": "Youness",
    "numero_examen": 1548,
    "salle_examen": "salle5",
    "epreuve": "MI"
  },
  {
    "id": "G140002673",
    "nom": "Sekkour",
    "prenom": "Marwa",
    "numero_examen": 1549,
    "salle_examen": "salle5",
    "epreuve": "MI"
  },
  {
    "id": "R130035305",
    "nom": "Sif",
    "prenom": "Souhail",
    "numero_examen": 1550,
    "salle_examen": "salle5",
    "epreuve": "MI"
  },
  {
    "id": "K110041058",
    "nom": "Souadi",
    "prenom": "Fatima",
    "numero_examen": 1551,
    "salle_examen": "salle5",
    "epreuve": "MI"
  },
  {
    "id": "R130063033",
    "nom": "Souihla",
    "prenom": "Marwa",
    "numero_examen": 1552,
    "salle_examen": "salle5",
    "epreuve": "MI"
  },
  {
    "id": "N149039257",
    "nom": "Soussi",
    "prenom": "Meryem",
    "numero_examen": 1553,
    "salle_examen": "salle6",
    "epreuve": "MI"
  },
  {
    "id": "M138425983",
    "nom": "Taghlaoui",
    "prenom": "Kamal",
    "numero_examen": 1554,
    "salle_examen": "salle6",
    "epreuve": "MI"
  },
  {
    "id": "M136201867",
    "nom": "Tahiri",
    "prenom": "Abdelali",
    "numero_examen": 1555,
    "salle_examen": "salle6",
    "epreuve": "MI"
  },
  {
    "id": "F130041339",
    "nom": "Tahiri",
    "prenom": "Abdelilah",
    "numero_examen": 1556,
    "salle_examen": "salle6",
    "epreuve": "MI"
  },
  {
    "id": "H137225198",
    "nom": "Tahiri",
    "prenom": "Douae",
    "numero_examen": 1557,
    "salle_examen": "salle6",
    "epreuve": "MI"
  },
  {
    "id": "D131652280",
    "nom": "Takachairou",
    "prenom": "Romaissa",
    "numero_examen": 1558,
    "salle_examen": "salle6",
    "epreuve": "MI"
  },
  {
    "id": "H120005065",
    "nom": "Taleb",
    "prenom": "Marwane",
    "numero_examen": 1559,
    "salle_examen": "salle6",
    "epreuve": "MI"
  },
  {
    "id": "G138265397",
    "nom": "Tamouch",
    "prenom": "Yahya",
    "numero_examen": 1560,
    "salle_examen": "salle6",
    "epreuve": "MI"
  },
  {
    "id": "2392210064",
    "nom": "Tangara",
    "prenom": "Baba Ibrahim",
    "numero_examen": 1561,
    "salle_examen": "salle6",
    "epreuve": "MI"
  },
  {
    "id": "M135492394",
    "nom": "Taouchikht",
    "prenom": "Lhoussin",
    "numero_examen": 1562,
    "salle_examen": "salle6",
    "epreuve": "MI"
  },
  {
    "id": "R110155464",
    "nom": "Taoussi",
    "prenom": "Zakaria",
    "numero_examen": 1563,
    "salle_examen": "salle6",
    "epreuve": "MI"
  },
  {
    "id": "G138797764",
    "nom": "Tarhzaoui",
    "prenom": "Hajar",
    "numero_examen": 1564,
    "salle_examen": "salle6",
    "epreuve": "MI"
  },
  {
    "id": "L120089400",
    "nom": "Tchabi",
    "prenom": "Fatima",
    "numero_examen": 1565,
    "salle_examen": "salle6",
    "epreuve": "MI"
  },
  {
    "id": "H120019208",
    "nom": "Tejjini",
    "prenom": "Rime",
    "numero_examen": 1566,
    "salle_examen": "salle6",
    "epreuve": "MI"
  },
  {
    "id": "H120011989",
    "nom": "Tekfaoui",
    "prenom": "Hanae",
    "numero_examen": 1567,
    "salle_examen": "salle6",
    "epreuve": "MI"
  },
  {
    "id": "2300000019",
    "nom": "Tiemtore",
    "prenom": "Djelika",
    "numero_examen": 1568,
    "salle_examen": "salle6",
    "epreuve": "MI"
  },
  {
    "id": "G130114587",
    "nom": "Tiheroui",
    "prenom": "Ibtissam",
    "numero_examen": 1569,
    "salle_examen": "salle6",
    "epreuve": "MI"
  },
  {
    "id": "F133125357",
    "nom": "Tiraoui",
    "prenom": "Mouhssine",
    "numero_examen": 1570,
    "salle_examen": "salle6",
    "epreuve": "MI"
  },
  {
    "id": "R120093067",
    "nom": "Tonzar",
    "prenom": "Abderrahim",
    "numero_examen": 1571,
    "salle_examen": "salle6",
    "epreuve": "MI"
  },
  {
    "id": "R110038647",
    "nom": "Toubali",
    "prenom": "Douae",
    "numero_examen": 1572,
    "salle_examen": "salle6",
    "epreuve": "MI"
  },
  {
    "id": "G134284966",
    "nom": "Touggani",
    "prenom": "Yassin",
    "numero_examen": 1573,
    "salle_examen": "salle6",
    "epreuve": "MI"
  },
  {
    "id": "S132037501",
    "nom": "Touibi",
    "prenom": "Chaymae",
    "numero_examen": 1574,
    "salle_examen": "salle6",
    "epreuve": "MI"
  },
  {
    "id": "H149057056",
    "nom": "Touil",
    "prenom": "Saif Yassine",
    "numero_examen": 1575,
    "salle_examen": "salle6",
    "epreuve": "MI"
  },
  {
    "id": "F133123186",
    "nom": "Wadii",
    "prenom": "Achraf",
    "numero_examen": 1576,
    "salle_examen": "salle6",
    "epreuve": "MI"
  },
  {
    "id": "D134069374",
    "nom": "Wakrimi",
    "prenom": "Mounia",
    "numero_examen": 1577,
    "salle_examen": "salle6",
    "epreuve": "MI"
  },
  {
    "id": "D132209745",
    "nom": "Wanaim",
    "prenom": "Abdelhakim",
    "numero_examen": 1578,
    "salle_examen": "salle6",
    "epreuve": "MI"
  },
  {
    "id": "H120005160",
    "nom": "Yahyaoui",
    "prenom": "Soumaya",
    "numero_examen": 1579,
    "salle_examen": "salle6",
    "epreuve": "MI"
  },
  {
    "id": "ET23FSR007",
    "nom": "Yanguendji",
    "prenom": "Jerahmeel Lilian",
    "numero_examen": 1580,
    "salle_examen": "salle6",
    "epreuve": "MI"
  },
  {
    "id": "R130258255",
    "nom": "Yaquine",
    "prenom": "Hamza",
    "numero_examen": 1581,
    "salle_examen": "salle6",
    "epreuve": "MI"
  },
  {
    "id": "H130174460",
    "nom": "Yoube",
    "prenom": "Ihsane",
    "numero_examen": 1582,
    "salle_examen": "salle6",
    "epreuve": "MI"
  },
  {
    "id": "R132664341",
    "nom": "Zaadane",
    "prenom": "Malak",
    "numero_examen": 1583,
    "salle_examen": "salle6",
    "epreuve": "MI"
  },
  {
    "id": "H146052771",
    "nom": "Zaazaa",
    "prenom": "Lina",
    "numero_examen": 1584,
    "salle_examen": "salle6",
    "epreuve": "MI"
  },
  {
    "id": "R138876117",
    "nom": "Zagour",
    "prenom": "Mohamed Zaid",
    "numero_examen": 1585,
    "salle_examen": "salle6",
    "epreuve": "MI"
  },
  {
    "id": "G130687273",
    "nom": "Zahid",
    "prenom": "Mariam",
    "numero_examen": 1586,
    "salle_examen": "salle6",
    "epreuve": "MI"
  },
  {
    "id": "M136452569",
    "nom": "Zaid",
    "prenom": "Salma",
    "numero_examen": 1587,
    "salle_examen": "salle6",
    "epreuve": "MI"
  },
  {
    "id": "D142019146",
    "nom": "Zaki",
    "prenom": "Zakaria",
    "numero_examen": 1588,
    "salle_examen": "salle6",
    "epreuve": "MI"
  },
  {
    "id": "H138142338",
    "nom": "Zekhnini",
    "prenom": "Miryam",
    "numero_examen": 1589,
    "salle_examen": "salle6",
    "epreuve": "MI"
  },
  {
    "id": "M120072398",
    "nom": "Zemzmi Alaoui",
    "prenom": "Inas",
    "numero_examen": 1590,
    "salle_examen": "salle6",
    "epreuve": "MI"
  },
  {
    "id": "H136124925",
    "nom": "Zerrouki",
    "prenom": "Soumaya",
    "numero_examen": 1591,
    "salle_examen": "salle6",
    "epreuve": "MI"
  },
  {
    "id": "R131918260",
    "nom": "Zilaoui",
    "prenom": "Doha",
    "numero_examen": 1592,
    "salle_examen": "salle6",
    "epreuve": "MI"
  },
  {
    "id": "E138118591",
    "nom": "Zineb",
    "prenom": "Benlafkih",
    "numero_examen": 1593,
    "salle_examen": "salle6",
    "epreuve": "MI"
  },
  {
    "id": "H120012181",
    "nom": "Zoufri",
    "prenom": "Islam",
    "numero_examen": 1594,
    "salle_examen": "salle6",
    "epreuve": "MI"
  },
  {
    "id": "G131136476",
    "nom": "Zougui",
    "prenom": "Sabir",
    "numero_examen": 1595,
    "salle_examen": "salle6",
    "epreuve": "MI"
  },
  {
    "id": "X231070012",
    "nom": "Zoungrana",
    "prenom": "Abdoul Gafarou",
    "numero_examen": 1596,
    "salle_examen": "salle6",
    "epreuve": "MI"
  },
  {
    "id": "2392210008",
    "nom": "Zoungrana",
    "prenom": "Nongwende Franck Vivien",
    "numero_examen": 1597,
    "salle_examen": "salle6",
    "epreuve": "MI"
  }
]